{"skeleton":{"hash":"lumeiAumK0i4oLAo/dWnLHgMtRk","spine":"3.7.93","width":6774.00,"height":5058.93},"bones":[{"name":"root"},{"name":"bone2","parent":"root","x":1205.07,"y":-4147.44},{"name":"bone200","parent":"bone2","length":1482.38,"x":989.94,"y":2249.73,"rotation":73.14},{"name":"bone180","parent":"bone200","x":1896.15,"y":144.97,"rotation":-73.14},{"name":"bone181","parent":"bone200","x":1845.32,"y":-176.48,"rotation":-73.14},{"name":"bone182","parent":"bone2","x":-536.64,"y":1788.52},{"name":"bone183","parent":"bone2","x":-168.81,"y":1574.41},{"name":"bone184","parent":"bone2","length":162.08,"x":-380.90,"y":1207.35,"rotation":-131.04},{"name":"bone185","parent":"bone2","length":258.37,"x":-1061.17,"y":1553.41,"rotation":-177.19},{"name":"bone186","parent":"bone2","length":494.19,"x":-2449.92,"y":2481.42,"rotation":137.09},{"name":"bone187","parent":"bone2","length":440.67,"x":-1804.79,"y":3753.18,"rotation":125.41},{"name":"bone188","parent":"bone2","length":681.14,"x":991.64,"y":2752.53,"rotation":84.98},{"name":"bone189","parent":"bone188","length":436.87,"x":951.30,"y":664.98,"rotation":67.12},{"name":"bone190","parent":"bone188","length":388.80,"x":1230.99,"y":283.61,"rotation":49.23},{"name":"bone191","parent":"bone188","length":506.99,"x":1209.79,"y":-335.52,"rotation":-36.77},{"name":"bone192","parent":"bone188","length":508.73,"x":1034.32,"y":-908.43,"rotation":-75.69},{"name":"bone193","parent":"bone2","length":393.71,"x":1758.84,"y":2424.96,"rotation":24.05},{"name":"bone194","parent":"bone2","length":230.04,"x":-1359.21,"y":3772.33,"rotation":-107.38},{"name":"bone195","parent":"bone2","length":239.33,"x":-1028.59,"y":3553.08,"rotation":-90.52},{"name":"bone196","parent":"bone2","length":429.10,"x":187.85,"y":2087.01,"rotation":-91.01},{"name":"bone197","parent":"bone196","length":283.52,"x":426.60,"y":-0.04370,"rotation":-6.62},{"name":"bone198","parent":"bone2","length":350.05,"x":938.30,"y":2473.25,"rotation":-56.99},{"name":"bone199","parent":"bone198","length":293.67,"x":350.05,"y":-1.2E-04,"rotation":-13.02},{"name":"bone201","parent":"bone2","x":-21.19,"y":1028.27},{"name":"bone202","parent":"bone2","length":635.37,"x":-2205.05,"y":3538.61,"rotation":165.47},{"name":"bone203","parent":"bone188","length":359.64,"x":392.79,"y":662.17,"rotation":74.44},{"name":"bone204","parent":"bone2","x":-1651.45,"y":5658.22},{"name":"fx_1","parent":"bone204","x":1723.23,"y":-817.51,"transform":"noScale"},{"name":"fx_2","parent":"bone204","x":1868.78,"y":-912.92,"transform":"noScale"},{"name":"fx_3","parent":"bone204","x":1950.20,"y":-968.17,"transform":"noScale"},{"name":"fx_4","parent":"bone204","x":2027.78,"y":-1006.89,"transform":"noScale"},{"name":"fx_5","parent":"bone204","x":2052.58,"y":-1023.00,"transform":"noScale"},{"name":"fx_6","parent":"bone204","x":1127.06,"y":-599.62,"transform":"noScale"},{"name":"bone209","parent":"bone2","x":74.93,"y":253.22},{"name":"bone210","parent":"bone209","x":707.07,"y":205.22},{"name":"bone211","parent":"bone209","x":575.91,"y":10.08},{"name":"bone212","parent":"bone209","x":844.63,"y":51.67}],"slots":[{"name":"bg_6","bone":"bone201","attachment":"bg_6"},{"name":"bubble_2","bone":"root","attachment":"bubble_2","blend":"additive"},{"name":"bubble_3","bone":"root","attachment":"bubble_2","blend":"additive"},{"name":"bubble_1","bone":"root","attachment":"bubble_1","blend":"additive"},{"name":"bubble_4","bone":"root","attachment":"bubble_1","blend":"additive"},{"name":"pin_light_4","bone":"bone2","attachment":"pin_light_1"},{"name":"pin_light_3","bone":"bone2","attachment":"pin_light_1"},{"name":"pin_light_2","bone":"bone2","attachment":"pin_light_1"},{"name":"fx_1","bone":"fx_1","color":"3e75bbff","attachment":"fx_1","blend":"additive"},{"name":"fx_2","bone":"fx_2","attachment":"fx_1","blend":"additive"},{"name":"fx_3","bone":"fx_3","color":"97dd5bff","attachment":"fx_1","blend":"additive"},{"name":"fx_4","bone":"fx_4","color":"285ab0ff","attachment":"fx_1","blend":"additive"},{"name":"fx_5","bone":"fx_5","attachment":"fx_1","blend":"additive"},{"name":"fx_6","bone":"fx_6","color":"c4a355ff","attachment":"fx_1","blend":"additive"},{"name":"bg_5","bone":"bone2","attachment":"bg_5"},{"name":"bg_14","bone":"bone2","attachment":"bg_5"},{"name":"bg_13","bone":"bone2","attachment":"bg_5"},{"name":"bg_4","bone":"bone200","attachment":"bg_4"},{"name":"bg_3","bone":"bone200","attachment":"bg_3"},{"name":"bg_2","bone":"bone2","attachment":"bg_2"},{"name":"bg_8","bone":"bone2","attachment":"bg_2"},{"name":"bg_11","bone":"bone200","attachment":"bg_2"},{"name":"bg_10","bone":"bone2","attachment":"bg_2"},{"name":"bg_9","bone":"bone2","attachment":"bg_2"},{"name":"bg_12","bone":"bone2","attachment":"bg_7"},{"name":"bg_7","bone":"bone2","attachment":"bg_2"},{"name":"pin_light_1","bone":"bone2","attachment":"pin_light_1"},{"name":"pin_light_5","bone":"bone2","attachment":"pin_light_1"},{"name":"2","bone":"root","color":"348e2bff","blend":"additive"},{"name":"1","bone":"root","color":"2f8c4eff","blend":"additive"}],"skins":{"default":{"bg_10":{"bg_2":{"type":"mesh","width":32,"height":32,"hull":6,"triangles":[4,3,2,4,2,1,5,4,1,0,5,1],"uvs":[0.82414,0.53784,1,0.33910,1,0,0.80401,0,0.81609,0.14016,0.80250,0.21527],"vertices":[-1175.87,4282.56,-2068.01,3519.22,-2068.01,2216.72,-1073.75,2216.72,-1135.03,2755.08,-1066.09,3043.57]}},"bg_11":{"bg_2":{"type":"mesh","width":32,"height":32,"hull":33,"triangles":[40,42,10,47,18,17,19,18,47,2,1,0,33,2,0,16,47,17,46,16,15,46,47,16,32,33,0,20,19,47,21,20,47,46,21,47,45,21,46,31,33,32,3,2,33,14,46,15,45,46,14,30,33,31,34,3,33,30,34,33,44,21,45,44,45,14,22,21,44,29,34,30,43,22,44,35,34,29,35,29,28,23,22,43,4,3,34,4,34,35,49,44,14,49,14,13,43,44,49,48,28,27,35,28,48,41,23,43,41,43,49,26,48,27,36,35,48,4,35,36,12,49,13,42,23,41,11,49,12,41,49,11,37,48,26,36,48,37,42,40,24,42,24,23,25,24,40,5,4,36,39,25,40,26,25,39,38,37,26,39,38,26,11,42,41,10,42,11,6,5,36,6,36,37,7,37,38,6,37,7,9,40,10,39,40,9,8,39,9,38,39,8,7,38,8],"uvs":[0.57702,0.05745,0.55511,0.04455,0.54283,0.06832,0.53334,0.10279,0.53695,0.13351,0.54156,0.16429,0.55788,0.17977,0.58384,0.19065,0.61078,0.19507,0.63207,0.19400,0.65161,0.17391,0.66752,0.15842,0.67855,0.15160,0.68054,0.11783,0.66952,0.10419,0.67775,0.07912,0.67273,0.05936,0.65584,0.05125,0.64021,0.04775,0.62946,0.06397,0.63463,0.08148,0.64677,0.09107,0.63518,0.10323,0.63393,0.12996,0.61858,0.13291,0.60839,0.14342,0.59387,0.14489,0.58592,0.12388,0.57378,0.12001,0.56596,0.11227,0.56764,0.10471,0.58131,0.09844,0.58271,0.07780,0.56007,0.08122,0.55211,0.10555,0.55393,0.12767,0.56119,0.14960,0.57835,0.16103,0.59398,0.16785,0.60961,0.16545,0.62790,0.16269,0.64785,0.14315,0.63850,0.15329,0.64967,0.12572,0.65218,0.11042,0.65651,0.09568,0.66083,0.07964,0.64520,0.06600,0.57462,0.13781,0.66404,0.13416],"vertices":[1,2,2234.53,73.40,1,1,2,2291.69,180.84,1,2,2,2204.90,249.33,0.82548,3,-10.34,325.75,0.17452,2,2,2076.17,306.55,0.73273,3,-102.43,219.15,0.26727,2,2,1957.20,296.47,0.59449,3,-127.28,102.36,0.40551,3,2,1837.63,281.36,0.45774,3,-147.51,-16.45,0.52281,4,-440.40,125.41,0.01944,3,2,1772.55,202.86,0.51500,3,-91.25,-101.50,0.41117,4,-384.14,40.36,0.07383,3,2,1721.74,74.39,0.57114,3,16.97,-187.39,0.18907,4,-275.93,-45.52,0.23979,3,2,1695.30,-60.75,0.61387,3,138.63,-251.88,0.03932,4,-154.27,-110.01,0.34681,3,2,1691.92,-168.79,0.57154,3,241.05,-286.45,0.00715,4,-51.85,-144.58,0.42131,2,2,1762.02,-273.03,0.49784,4,68.24,-107.72,0.50216,2,2,1815.75,-357.67,0.61944,4,164.83,-80.85,0.38056,2,2,1838,-415.29,0.63846,4,226.42,-76.27,0.36154,2,2,1966.72,-434.40,0.74170,4,282.04,41.38,0.25830,3,2,2022.87,-382.24,0.69003,3,541.30,-31.62,0.05923,4,248.40,110.25,0.25074,2,2,2116.03,-430.59,0.96065,4,321.70,185.38,0.03935,1,2,2193.48,-410.44,1,1,2,2230.51,-327.13,1,1,2,2249.43,-248.97,1,2,2,2191.06,-190.26,0.94535,4,113.45,326.89,0.05465,2,2,2122.15,-211.72,0.87982,4,114,254.71,0.12018,2,2,2081.14,-270.61,0.74139,4,158.47,198.39,0.25861,2,2,2038.61,-208.74,0.75253,4,86.93,175.62,0.24747,2,2,1936.64,-195.26,0.62105,4,44.45,81.95,0.37895,3,2,1930.75,-116.79,0.66696,3,260.54,-42.80,0.06033,4,-32.36,99.06,0.27271,3,2,1894.07,-62.42,0.58017,3,197.88,-62.13,0.14473,4,-95.02,79.73,0.27511,3,2,1893.54,11.42,0.48679,3,127.05,-41.23,0.29466,4,-165.85,100.63,0.21856,3,2,1976.85,46.08,0.70967,3,118.04,48.56,0.22131,4,-174.85,190.42,0.06903,3,2,1995.96,106.50,0.73595,3,65.77,84.37,0.23718,4,-227.13,226.23,0.02687,2,2,2028.38,143.98,0.74876,3,39.29,126.26,0.25124,2,2,2056.75,133.49,0.80551,3,57.56,150.37,0.19449,2,2,2075.94,62.61,0.95136,3,130.96,148.18,0.04864,2,2,2154.56,50.04,0.93392,3,165.79,219.77,0.06608,2,2,2149.43,165.52,0.78612,3,53.78,248.36,0.21388,2,2,2059,212.27,0.64446,3,-17.18,175.37,0.35554,3,2,1973.61,208.99,0.64344,3,-38.80,92.70,0.35136,4,-331.70,234.56,0.00521,3,2,1887.01,178.11,0.49714,3,-34.37,0.86000,0.43428,4,-327.26,142.72,0.06858,3,2,1837.17,94.28,0.40786,3,31.40,-71.14,0.39622,4,-261.49,70.72,0.19591,3,2,1805.53,17,0.44420,3,96.19,-123.84,0.25922,4,-196.70,18.03,0.29659,3,2,1809.21,-62.75,0.47812,3,173.58,-143.44,0.13472,4,-119.32,-1.58,0.38717,3,2,1813.36,-156.01,0.48573,3,264.04,-166.51,0.03053,4,-28.86,-24.65,0.48374,2,2,1881.20,-262.22,0.51593,4,92.46,9.47,0.48407,3,2,1845.65,-212.19,0.47805,3,327.17,-151.91,0.00302,4,34.27,-10.04,0.51893,3,2,1947.34,-276.05,0.60654,3,417.77,-73.11,0.00901,4,124.87,68.76,0.38444,3,2,2005.08,-292.84,0.58723,3,450.58,-22.72,0.06230,4,157.69,119.14,0.35047,3,2,2060.06,-318.67,0.67220,3,491.24,22.41,0.06121,4,198.35,164.27,0.26660,2,2,2119.98,-344.84,0.85642,4,240.77,214.03,0.14358,2,2,2177.75,-269.37,0.92378,4,185.30,291.20,0.07622,3,2,1927.47,106.97,0.54914,3,45.45,18.95,0.33217,4,-247.45,160.82,0.11869,2,2,1909.94,-346.54,0.64023,4,181.49,12.52,0.35977]}},"bg_12":{"bg_7":{"type":"mesh","width":32,"height":32,"hull":27,"triangles":[23,24,37,43,30,46,37,38,30,24,25,38,30,31,46,47,51,48,51,5,6,25,26,39,31,38,39,25,39,38,39,0,27,39,27,32,31,32,49,31,39,32,31,49,46,50,47,49,50,49,52,51,50,52,49,53,52,53,27,2,32,27,53,52,53,3,3,53,2,52,3,4,0,2,27,0,1,2,4,51,52,5,51,4,32,53,49,26,0,39,47,46,49,47,50,51,48,51,6,30,38,31,43,46,47,37,24,38,41,40,44,41,44,45,42,41,45,42,45,8,42,8,9,13,40,41,13,41,42,14,40,13,12,13,42,11,42,9,12,42,11,10,11,9,48,6,7,44,47,48,45,44,48,43,47,44,7,45,48,8,45,7,21,22,33,17,33,16,21,33,17,18,21,17,20,21,18,19,20,18,29,37,30,37,36,23,35,37,29,29,30,43,35,36,37,22,23,36,34,36,35,28,35,29,28,29,43,34,35,28,40,28,43,40,43,44,33,22,36,33,36,34,16,34,28,15,16,28,15,28,40,14,15,40,16,33,34],"uvs":[0.20587,0.11701,0.18044,0.00993,0.39699,0,0.83587,0,0.87918,0.11380,0.94234,0.27013,0.98024,0.45538,1,0.61926,0.99999,0.74434,1.00000,0.88189,0.97938,1,0.95294,1,0.83541,0.95248,0.69806,0.92285,0.55776,0.91587,0.43069,0.89408,0.31918,0.85459,0.18770,0.89295,0.07899,0.92694,0,0.96355,0,0.92869,0.04888,0.81450,0.12063,0.68147,0.18600,0.55594,0.24476,0.44175,0.24770,0.33745,0.23448,0.23459,0.41843,0.09803,0.43401,0.75258,0.44281,0.60953,0.46192,0.47026,0.47349,0.34416,0.45216,0.20438,0.17641,0.79651,0.32698,0.74275,0.33660,0.62082,0.24388,0.63946,0.34049,0.51250,0.35586,0.36279,0.34447,0.21987,0.57322,0.78898,0.71229,0.79646,0.87474,0.84479,0.58235,0.62627,0.73287,0.64907,0.89821,0.67926,0.58627,0.44989,0.72199,0.45681,0.85483,0.48754,0.58445,0.28996,0.75792,0.30087,0.85206,0.30435,0.76833,0.11000,0.57284,0.10332],"vertices":[1,1,-66.43,2309.50,1,1,1,-151.99,2401.97,1,1,1,102.64,2542.05,1,1,1,628.86,2805.60,1,1,1,738.38,2716.63,1,5,19,-521.89,696.32,0.01722,20,-1022.47,582.32,0,21,-128,29.38,0.03919,22,-472.37,-79.10,0.01042,1,893.22,2596.60,0.93318,5,19,-359.95,838.36,0.09051,20,-877.99,742.09,1.0E-05,21,85.69,56.54,0.34286,22,-270.30,-4.49,0.16507,1,1032.40,2432.19,0.40155,5,19,-208.13,947.66,0.07074,20,-739.80,868.17,1.0E-04,21,272.67,62.22,0.42016,22,-89.41,43.18,0.34775,1,1139.01,2278.48,0.16125,4,19,-82.87,1013.15,0.05358,20,-622.92,947.67,5.6E-04,21,413.14,46.44,0.39221,22,51,59.47,0.55365,4,19,54.86,1085.19,0.05441,20,-494.42,1035.11,0.00212,21,567.60,29.12,0.27602,22,205.39,77.39,0.66745,4,19,185.93,1122.54,0.08350,20,-368.53,1087.33,0.00662,21,697.14,-13.24,0.17739,22,341.15,65.32,0.73249,4,19,202.37,1091.11,0.13798,20,-348.58,1058.01,0.01745,21,693.19,-48.48,0.10939,22,345.24,30.09,0.73518,4,19,227.82,926.57,0.21277,20,-304.32,897.51,0.03963,21,622.25,-199.11,0.07227,22,310.07,-132.65,0.67533,4,19,283.50,747.83,0.29865,20,-228.39,726.38,0.07864,21,568.43,-378.42,0.05823,22,298.04,-319.47,0.56449,4,19,363.71,577.47,0.38326,20,-129.08,566.41,0.13795,21,539.61,-564.50,0.05768,22,311.90,-507.26,0.42111,4,19,420.86,415.05,0.45520,20,-53.58,411.67,0.21589,21,496.14,-731.10,0.06360,22,307.08,-679.37,0.26530,4,19,450.61,261.87,0.38750,20,-6.35,262.94,0.38354,21,435.12,-874.72,0.04478,22,280,-833.05,0.18418,4,19,570.73,125.72,0.31927,20,128.66,141.54,0.53460,21,458.52,-1054.77,0.02905,22,343.38,-1003.19,0.11708,4,19,672.32,14.34,0.27351,20,242.43,42.63,0.64177,21,480.44,-1203.92,0.01709,22,398.34,-1143.57,0.06762,4,19,758.07,-60.36,0.27114,20,336.22,-21.68,0.68464,21,509.74,-1313.80,0.00908,22,451.65,-1244.02,0.03513,4,19,723.16,-78.62,0.32244,20,303.65,-43.84,0.65668,21,470.58,-1309.41,0.00466,22,412.51,-1248.57,0.01622,4,19,578.44,-80.33,0.42181,20,160.09,-62.24,0.56815,21,349.66,-1229.88,0.00349,22,276.78,-1198.34,0.00656,5,19,400.65,-64.74,0.51014,20,-18.31,-67.25,0.41163,21,211.01,-1117.50,0.00573,22,116.37,-1120.09,0.00213,1,116.10,1687.56,0.07037,5,19,234.33,-52.79,0.44717,20,-184.90,-74.56,0.20514,21,79.83,-1014.57,0.01010,22,-34.63,-1049.36,4.9E-04,1,130.97,1853.64,0.33710,5,19,83.47,-42.76,0.30811,20,-335.91,-82,0.07690,21,-39.61,-921.87,0.01431,22,-171.89,-985.96,1.8E-04,1,143.64,2004.30,0.60050,5,19,-22.80,-93.89,0.10987,20,-435.57,-145.05,0.01411,21,-156.30,-904.81,0.01007,22,-289.43,-995.64,1.2E-04,1,94.38,2111.45,0.86582,1,1,26.48,2207.44,1,1,1,177.94,2455.87,1,5,19,277.10,344.90,0.56725,20,-188.28,325.40,0.13826,21,337.73,-708.84,0.09159,22,147.74,-693.38,0.19690,1,527.84,1803.90,0.00599,5,19,128.39,280.45,0.52426,20,-328.56,244.23,0.06432,21,178.42,-679.08,0.09773,22,-14.19,-700.29,0.11250,1,466.01,1953.71,0.20119,5,19,-22.94,230.23,0.37591,20,-473.09,176.89,0.02211,21,24.88,-636.06,0.08198,22,-173.47,-692.98,0.05029,1,418.45,2105.91,0.46970,5,19,-156.40,177.94,0.14294,20,-599.63,109.56,0.00378,21,-115,-604.75,0.03731,22,-316.80,-693.99,0.01165,1,368.51,2240.26,0.80432,1,1,272.20,2368.67,1,4,19,481.17,61.80,0.16057,20,47.08,67.72,0.83333,21,348.53,-1057.66,5.1E-04,22,236.87,-1030.80,0.00559,5,19,333.77,212.57,0.78214,20,-116.73,200.48,0.10699,21,310.69,-850.23,0.02312,22,153.25,-837.23,0.07116,1,394.53,1749.56,0.01659,5,19,205.70,160.16,0.74259,20,-237.90,133.65,0.00497,21,175.21,-822.04,0.02377,22,14.91,-840.29,0.03635,1,344.38,1878.53,0.19231,5,19,281.99,59.74,0.83707,20,-150.54,42.70,0.00205,21,182.28,-947.95,0.00271,22,50.17,-961.38,0.00755,1,242.63,1804.01,0.15062,4,19,94.82,108.05,0.53716,21,54.15,-803.21,0.01644,22,-107.28,-849.23,0.01139,1,294.22,1990.30,0.43501,4,19,-64.64,47.92,0.21229,21,-111.66,-763.85,0.01011,22,-277.70,-848.25,9.9E-04,1,236.90,2150.80,0.77661,1,1,150.92,2288.37,1,4,19,227.03,529.39,0.50678,20,-259.29,502.88,0.00394,21,399.43,-527.91,0.13082,22,167.07,-503.20,0.35846,3,19,148.11,698.56,0.25572,21,428.63,-343.53,0.15942,22,153.97,-316.99,0.58486,3,19,95.54,916.92,0.03351,21,507.20,-133.13,0.01924,22,183.11,-94.29,0.94725,5,19,58.44,455.03,0.43145,20,-418.19,409.58,7.0E-05,21,218.08,-495.24,0.21246,22,-16.97,-512.24,0.17868,1,641.79,2020.60,0.17735,4,19,-12.27,645.84,0.20559,21,266.20,-297.52,0.37328,22,-14.65,-308.76,0.29576,1,833.81,2087.95,0.12537,4,19,-84.79,858.12,0.02128,21,324.83,-80.99,0.51137,22,-6.32,-84.59,0.39729,1,1047.33,2156.73,0.07006,4,19,-120.61,367.33,0.27237,21,20.61,-467.78,0.19451,22,-215.55,-529.99,0.03793,1,557.24,2201.16,0.49519,4,19,-198.03,532.22,0.14940,21,48.67,-287.79,0.37056,22,-228.77,-348.30,0.04136,1,723.47,2275.67,0.43867,4,19,-249.81,706.17,0.03673,21,103.04,-114.64,0.58427,22,-214.82,-167.35,0.01928,1,898.29,2324.39,0.35972,4,19,-279.62,281.41,0.04314,21,-159.26,-450.05,0.03412,22,-394.79,-553.25,0.00126,1,474.13,2361.65,0.92148,4,19,-376.50,493.26,0.02718,21,-121.06,-220.26,0.09312,22,-409.36,-320.76,0.00105,1,687.64,2454.80,0.87865,4,19,-431.52,606.95,0.01676,21,-103.08,-95.24,0.16743,22,-420.01,-194.90,2.3E-04,1,802.28,2507.82,0.81558,1,1,603.54,2653.89,1,1,1,365.76,2543.26,1]}},"bg_13":{"bg_5":{"type":"mesh","width":32,"height":32,"hull":102,"triangles":[137,131,130,137,130,136,136,35,36,136,130,35,130,34,35,33,130,32,34,130,33,31,130,131,31,32,130,30,31,131,19,20,21,19,21,18,113,7,8,1,2,3,5,113,114,5,6,113,4,5,114,6,7,113,92,104,91,90,91,104,104,109,89,89,90,104,94,120,93,120,94,95,120,95,119,96,97,119,95,96,119,119,97,118,98,117,97,97,117,118,92,93,104,98,99,117,93,121,116,93,103,104,93,116,103,104,103,109,119,121,120,93,120,121,118,111,119,119,111,121,118,99,110,110,99,100,99,118,117,118,110,111,121,111,116,88,89,109,108,88,109,116,111,112,111,110,112,116,102,103,102,116,115,108,109,103,108,67,88,103,102,108,108,102,105,0,1,101,101,122,100,101,1,122,112,110,122,110,100,122,105,106,108,106,107,108,116,112,115,115,124,102,102,124,105,122,4,112,112,4,115,122,1,3,122,3,4,88,67,87,4,114,115,115,114,124,67,108,66,87,67,68,66,108,107,114,123,124,124,123,105,105,123,106,87,68,86,114,113,9,114,9,123,9,113,8,86,68,69,65,66,107,107,106,125,106,123,125,123,9,125,107,127,65,127,128,65,125,126,107,107,126,127,86,69,85,84,85,153,85,69,153,84,153,83,65,128,64,70,153,69,9,10,125,10,11,125,126,11,12,126,125,11,82,83,154,83,153,154,81,82,155,153,70,154,127,126,129,82,154,155,155,156,81,81,156,80,126,12,129,129,135,127,127,141,128,127,135,141,154,70,71,64,128,152,80,157,79,80,156,157,154,71,155,79,157,78,64,152,63,150,152,128,155,71,72,62,63,152,12,13,129,157,77,78,155,72,156,135,129,27,135,140,141,128,141,150,141,140,150,72,73,156,156,74,157,156,73,74,129,13,27,27,134,135,135,134,140,13,14,27,61,62,152,61,151,60,151,61,152,74,75,157,157,76,77,157,75,76,151,47,60,152,150,151,14,26,27,133,27,28,27,133,134,151,150,149,134,133,140,133,139,140,149,150,139,150,140,139,14,15,26,47,59,60,151,149,47,26,15,25,15,16,25,133,28,132,29,132,28,133,132,139,16,24,25,16,17,24,58,59,57,132,138,139,139,138,149,59,56,57,148,149,144,149,148,47,144,149,138,47,48,59,47,148,46,59,48,56,24,17,23,17,18,23,18,22,23,18,21,22,56,48,49,132,29,30,55,56,49,148,45,46,49,50,55,55,50,54,30,131,132,132,131,138,45,148,44,131,137,138,138,137,144,44,148,147,50,51,54,54,51,53,142,144,143,148,144,147,144,142,147,143,144,137,51,52,53,44,147,43,147,146,43,147,142,146,146,142,38,137,136,143,43,146,42,42,146,145,37,143,36,142,143,38,143,37,38,36,143,136,146,38,145,42,145,41,38,39,145,145,40,41,145,39,40],"uvs":[0.40808,0.77508,0.43430,0.74696,0.43669,0.70803,0.47828,0.70803,0.51404,0.70370,0.49364,0.61827,0.47801,0.53446,0.52013,0.54041,0.55351,0.55555,0.58344,0.58475,0.59704,0.53038,0.62750,0.51145,0.66618,0.50496,0.63015,0.47468,0.60737,0.40980,0.59465,0.36438,0.56192,0.34275,0.52987,0.30436,0.49358,0.28976,0.45888,0.27787,0.44457,0.24056,0.47424,0.22163,0.50974,0.22542,0.54656,0.23731,0.57835,0.28381,0.61384,0.32220,0.63716,0.37087,0.65750,0.41893,0.64003,0.36377,0.61686,0.28538,0.59024,0.20990,0.56801,0.11367,0.56313,0.03280,0.57715,0,0.62246,0,0.65294,0,0.70333,0.02524,0.74519,0.03146,0.78582,0.08040,0.81738,0.04998,0.84705,0.03546,0.87915,0.04666,0.86838,0.09311,0.84237,0.14744,0.82004,0.19234,0.82918,0.24294,0.83329,0.28161,0.82292,0.32475,0.83979,0.28617,0.85970,0.23848,0.88937,0.20986,0.92533,0.18747,0.96346,0.18174,0.96874,0.22446,0.94131,0.23980,0.90454,0.27423,0.87893,0.28376,0.89112,0.33312,0.87702,0.34148,0.85467,0.32240,0.86970,0.37839,0.87580,0.43355,0.85245,0.47777,0.84220,0.51220,0.79361,0.52505,0.78240,0.59535,0.76938,0.65748,0.76237,0.71798,0.78020,0.65666,0.80463,0.59413,0.82545,0.53936,0.84624,0.50963,0.86511,0.47058,0.88697,0.43518,0.91567,0.42468,0.95031,0.41447,0.97883,0.42829,1,0.44275,1,0.50207,0.97608,0.52713,0.95152,0.53686,0.92912,0.54735,0.90546,0.57902,0.87532,0.58376,0.85184,0.60100,0.83505,0.60742,0.81707,0.62927,0.78952,0.66919,0.77558,0.73124,0.76045,0.84428,0.79075,1,0.76344,1,0.67505,0.94123,0.63445,0.89851,0.65006,0.97119,0.60102,1,0.54699,1,0.49607,0.95516,0.44860,0.90607,0.46953,0.84678,0.48858,0.81108,0.44048,0.82447,0.62722,0.78737,0.67949,0.83164,0.73283,0.89261,0.64571,0.70462,0.66669,0.64656,0.69762,0.63930,0.72003,0.72277,0.73638,0.84761,0.51889,0.81207,0.56476,0.84111,0.53560,0.77288,0.52031,0.58345,0.55872,0.65748,0.58432,0.72643,0.61739,0.83312,0.48369,0.87957,0.53276,0.87377,0.57187,0.88030,0.60814,0.88973,0.60672,0.86506,0.48724,0.75982,0.61324,0.64626,0.62320,0.70577,0.63244,0.58820,0.67848,0.54913,0.71543,0.54159,0.74953,0.53926,0.67568,0.49475,0.61807,0.07746,0.64056,0.17285,0.66551,0.27327,0.68554,0.35503,0.70100,0.41241,0.70978,0.47552,0.67254,0.07244,0.69081,0.15134,0.71084,0.25103,0.72138,0.33997,0.72454,0.41169,0.72771,0.47839,0.76180,0.15755,0.73123,0.12241,0.75122,0.22601,0.83590,0.07970,0.80849,0.11771,0.78987,0.17007,0.76914,0.25398,0.75895,0.33073,0.75895,0.41751,0.80428,0.38954,0.79619,0.45696,0.82911,0.56271,0.85588,0.52929,0.87886,0.49651,0.91381,0.47595,0.96136,0.46566],"vertices":[2,1,-3074.16,2456.68,0.47929,9,440.36,443.13,0.52071,2,1,-2949.22,2522.30,0.48964,9,393.53,310,0.51036,2,1,-2937.86,2613.16,0.46494,9,447.08,235.72,0.53506,2,1,-2739.73,2613.17,0.49344,9,301.96,100.82,0.50656,2,1,-2569.36,2623.26,0.49594,9,184.05,-22.57,0.50406,2,1,-2666.53,2822.66,0.37645,9,390.98,-102.45,0.62355,3,1,-2740.99,3018.27,0.38299,9,578.70,-195.02,0.60989,24,388.21,638.19,0.00711,2,1,-2540.33,3004.39,0.46485,9,422.28,-321.47,0.53515,2,1,-2381.32,2969.05,0.56883,9,281.76,-403.86,0.43117,2,1,-2238.72,2900.91,0.66466,9,130.91,-451.04,0.33534,3,1,-2173.96,3027.81,0.83449,9,169.89,-588.08,0.15888,24,-158.28,486.64,0.00663,3,1,-2028.83,3071.99,0.95685,9,93.67,-719.24,0.04120,24,-287.68,407.46,0.00194,1,1,-1844.58,3087.13,1,3,1,-2016.21,3157.80,0.94224,9,142.85,-790.69,0.01946,24,-278.36,321.23,0.03829,3,1,-2124.74,3309.24,0.91359,9,325.45,-827.71,0.00524,24,-135.29,201.87,0.08117,2,1,-2185.32,3415.25,0.88158,24,-50.05,114.46,0.11842,2,1,-2341.24,3465.73,0.66665,24,113.54,104.72,0.33335,2,1,-2493.94,3555.33,0.48373,24,283.85,56.31,0.51627,2,1,-2666.83,3589.40,0.45418,24,459.76,66.72,0.54582,2,1,-2832.16,3617.16,0.34370,24,626.76,81.34,0.65630,2,1,-2900.30,3704.24,0.37226,24,714.58,14.15,0.62774,2,1,-2758.96,3748.41,0.47646,24,588.84,-64.08,0.52354,2,1,-2589.85,3739.58,0.61329,24,422.93,-97.97,0.38671,2,1,-2414.44,3711.82,0.63741,24,246.16,-115.12,0.36259,2,1,-2263,3603.29,0.82177,24,72.33,-48.07,0.17823,3,1,-2093.89,3513.69,0.92350,24,-113.86,-3.78,0.05964,10,-27.67,374.40,0.01685,1,1,-1982.83,3400.11,1,1,1,-1885.91,3287.93,1,2,1,-1969.16,3416.67,0.91408,10,-179.02,328.95,0.08592,3,1,-2079.51,3599.62,0.62970,24,-106.21,-90.57,0.02430,10,34.04,312.88,0.34601,3,1,-2206.32,3775.80,0.56312,24,60.76,-229.28,0.01712,10,251.10,314.15,0.41976,2,1,-2312.27,4000.40,0.28501,10,495.54,270.35,0.71499,2,1,-2335.50,4189.16,0.11609,10,662.85,179.91,0.88391,2,1,-2268.71,4265.71,0.11678,10,686.53,81.11,0.88322,2,1,-2052.85,4265.71,0.21567,10,561.45,-94.82,0.78433,2,1,-1907.65,4265.71,0.38624,10,477.32,-213.16,0.61376,2,1,-1667.59,4206.81,0.55393,10,290.21,-374.67,0.44607,2,1,-1468.18,4192.29,0.66496,10,162.83,-528.78,0.33504,2,1,-1274.58,4078.07,0.85913,10,-42.45,-620.38,0.14087,2,1,-1124.24,4149.06,0.86782,10,-71.70,-784.04,0.13218,2,1,-982.91,4182.94,0.86878,10,-125.98,-918.86,0.13122,2,1,-829.97,4156.81,0.92262,10,-235.91,-1028.37,0.07738,2,1,-881.27,4048.39,0.92128,10,-294.54,-923.73,0.07872,2,1,-1005.17,3921.58,0.93166,10,-326.09,-749.27,0.06834,2,1,-1111.59,3816.80,0.93635,10,-349.83,-601.82,0.06365,2,1,-1068.03,3698.70,0.98020,10,-471.32,-568.89,0.01980,1,1,-1048.47,3608.43,1,1,1,-1097.83,3507.76,1,1,1,-1017.49,3597.79,1,1,1,-922.63,3709.11,1,1,1,-781.30,3775.90,1,1,1,-609.96,3828.17,1,1,1,-428.32,3841.54,1,1,1,-403.15,3741.84,1,1,1,-533.83,3706.02,1,1,1,-709.04,3625.68,1,1,1,-831,3603.41,1,1,1,-772.92,3488.22,1,1,1,-840.14,3468.72,1,1,1,-946.62,3513.24,1,1,1,-874.98,3382.56,1,1,1,-845.94,3253.82,1,1,1,-957.17,3150.61,1,1,1,-1006.01,3070.25,1,1,1,-1237.47,3040.25,1,1,1,-1290.89,2876.16,1,1,1,-1352.90,2731.15,1,1,1,-1386.29,2589.96,1,1,1,-1301.38,2733.06,1,1,1,-1185,2879.02,1,1,1,-1085.78,3006.86,1,1,1,-986.75,3076.23,1,1,1,-896.88,3167.39,1,1,1,-792.73,3250,1,1,1,-655.99,3274.51,1,1,1,-490.96,3298.35,1,1,1,-355.08,3266.11,1,1,1,-254.24,3232.35,1,1,1,-254.24,3093.89,1,1,1,-368.18,3035.41,1,1,1,-485.17,3012.70,1,1,1,-591.93,2988.22,1,1,1,-704.62,2914.28,1,1,1,-848.20,2903.22,1,1,1,-960.08,2862.99,1,1,1,-1040.04,2848,1,1,1,-1125.72,2797,1,1,1,-1256.95,2703.84,1,1,1,-1323.39,2559,1,1,1,-1395.46,2295.16,1,1,1,-1251.07,1931.72,1,1,1,-1381.19,1931.72,1,1,1,-1802.29,2068.89,1,2,1,-1995.73,2168.58,0.96132,9,-545.65,-80.10,0.03868,2,1,-1921.33,1998.95,0.99383,9,-715.64,-6.51,0.00617,2,1,-2154.96,1931.71,0.89207,9,-590.30,201.80,0.10793,2,1,-2412.39,1931.71,0.77385,9,-401.76,377.07,0.22615,2,1,-2654.93,2036.36,0.61883,9,-152.87,465.56,0.38117,2,1,-2881.11,2150.93,0.53251,9,90.80,535.63,0.46749,2,1,-2781.41,2289.31,0.54890,9,112,366.40,0.45110,2,1,-2690.64,2372.64,0.62755,9,102.25,243.57,0.37245,2,1,-2919.80,2341.39,0.54123,9,248.81,422.47,0.45877,2,1,-2030.16,2428,0.87581,9,-343.81,-246.66,0.12419,1,1,-1781.14,2324.67,1,1,1,-1527.04,2182.37,1,2,1,-1942.08,2621.12,0.91884,9,-276.85,-448.08,0.08116,2,1,-1842.13,2756.64,0.97477,9,-257.78,-615.39,0.02523,1,1,-1694.75,2773.58,1,1,1,-1588.03,2578.77,1,1,1,-1510.10,2287.40,1,2,1,-2546.24,2370.33,0.61637,9,-5.09,146.95,0.38363,2,1,-2327.72,2302.57,0.71545,9,-211.28,47.79,0.28455,2,1,-2466.63,2461.80,0.59234,9,-1.12,25.74,0.40766,2,1,-2539.47,2903.94,0.40426,9,353.26,-248.49,0.59574,2,1,-2356.52,2731.15,0.50707,9,101.62,-246.50,0.49293,2,1,-2234.55,2570.22,0.66595,9,-97.28,-211.67,0.33405,2,1,-2077,2321.20,0.88110,9,-382.22,-136.55,0.11890,2,1,-2713.95,2212.78,0.54088,9,10.48,376.52,0.45912,2,1,-2480.18,2226.34,0.60095,9,-151.51,207.43,0.39905,2,1,-2293.84,2211.09,0.75300,9,-298.37,91.73,0.24700,2,1,-2121.05,2189.07,0.90013,9,-439.92,-9.79,0.09987,2,1,-2127.82,2246.67,0.88235,9,-395.74,-47.36,0.11765,2,1,-2697.01,2492.29,0.60031,9,188.38,160.27,0.39969,2,1,-2096.77,2757.34,0.77666,9,-70.80,-442.54,0.22334,2,1,-2049.33,2618.43,0.82044,9,-200.12,-373.09,0.17956,2,1,-2005.29,2892.86,0.90079,9,-45.53,-604.07,0.09921,1,1,-1785.96,2984.05,1,1,1,-1609.94,3001.65,1,1,1,-1447.46,3007.07,1,1,1,-1799.30,3110.96,1,2,1,-2073.74,4084.91,0.23960,10,426.21,26.98,0.76040,2,1,-1966.61,3862.27,0.54098,10,182.67,68.67,0.45902,2,1,-1847.75,3627.91,0.83669,10,-77.20,107.60,0.16331,2,1,-1752.33,3437.08,0.98578,10,-288.03,140.42,0.01422,1,1,-1678.67,3303.16,1,1,1,-1636.82,3155.84,1,2,1,-1814.27,4096.63,0.44308,10,285.41,-191.28,0.55692,2,1,-1727.22,3912.49,0.69732,10,84.89,-155.53,0.30268,2,1,-1631.81,3679.81,0.88350,10,-160.04,-98.46,0.11650,1,1,-1581.58,3472.23,1,1,1,-1566.52,3304.83,1,1,1,-1551.45,3149.15,1,2,1,-1389.01,3897.99,0.85248,10,-122.91,-422.77,0.14752,2,1,-1534.65,3980.01,0.81476,10,28.33,-351.60,0.18524,2,1,-1439.45,3738.21,0.90473,10,-223.91,-289.08,0.09527,2,1,-1036.02,4079.70,0.87704,10,-179.35,-815.76,0.12296,2,1,-1166.59,3990.98,0.87555,10,-176,-657.93,0.12445,2,1,-1255.31,3868.78,0.88531,10,-224.19,-514.81,0.11469,2,1,-1354.07,3672.92,0.92604,10,-326.59,-320.83,0.07396,2,1,-1402.62,3493.80,0.99274,10,-444.44,-177.47,0.00726,1,1,-1402.62,3291.25,1,1,1,-1186.67,3356.54,1,1,1,-1225.17,3199.18,1,1,1,-1068.33,2952.36,1,1,1,-940.83,3030.36,1,1,1,-831.33,3106.86,1,1,1,-664.84,3154.86,1,1,1,-438.33,3178.86,1]}},"bg_14":{"bg_5":{"type":"mesh","width":32,"height":32,"hull":69,"triangles":[26,30,29,26,25,30,26,29,27,24,31,25,25,31,30,27,29,28,89,42,41,50,47,46,50,49,47,47,49,48,60,59,81,59,58,54,58,55,54,58,57,55,57,56,55,81,59,54,53,81,54,75,5,74,73,66,74,68,67,73,72,0,68,72,68,73,4,3,73,73,3,72,3,2,72,2,1,72,1,0,72,4,73,74,5,4,74,73,67,66,11,71,12,10,9,11,11,9,8,11,8,71,8,7,71,71,70,12,88,96,12,70,88,12,7,77,71,70,71,77,13,12,20,7,6,77,14,13,20,20,12,96,15,14,19,15,19,18,20,19,14,70,87,88,70,77,76,16,18,17,16,15,18,69,87,70,76,77,6,76,6,75,96,88,86,88,87,86,94,96,86,94,20,96,6,5,75,70,76,69,86,87,80,80,87,69,76,75,69,94,95,20,20,95,21,80,85,86,80,102,85,75,65,69,69,65,80,75,74,65,86,85,94,21,95,22,94,93,95,94,85,93,95,34,22,95,93,34,65,74,66,65,64,80,64,79,80,80,79,102,64,63,79,79,63,62,78,62,61,62,78,79,22,34,23,23,34,33,93,35,34,85,101,84,92,93,84,93,85,84,79,101,102,85,102,101,79,78,101,33,32,23,23,32,24,92,35,93,32,31,24,78,100,101,101,100,84,60,81,61,35,92,36,61,53,78,78,53,100,100,83,84,84,97,92,84,83,97,92,91,36,92,97,91,61,81,53,36,91,37,53,52,100,100,52,83,97,99,91,91,90,37,91,99,90,97,83,82,38,90,39,38,37,90,83,52,82,97,98,99,97,82,98,52,51,82,82,51,46,51,50,46,82,46,98,39,90,89,90,99,89,39,89,40,89,99,44,46,45,98,99,98,44,98,45,44,40,89,41,44,43,89,89,43,42],"uvs":[0,0.55361,0,0.59205,0,0.65326,0.03327,0.66189,0.08049,0.68413,0.11742,0.72330,0.16267,0.74416,0.21150,0.80767,0.23886,0.89857,0.24852,1,0.28607,1,0.29412,0.90733,0.31558,0.80877,0.34765,0.79976,0.38158,0.79022,0.41007,0.76717,0.43566,0.74646,0.43395,0.69882,0.40644,0.68642,0.37665,0.67906,0.34344,0.68875,0.36469,0.64304,0.39997,0.59103,0.43431,0.51821,0.47888,0.46089,0.51361,0.42719,0.55064,0.41511,0.59808,0.39768,0.59902,0.36127,0.55424,0.34423,0.49845,0.35430,0.46183,0.39652,0.41950,0.44714,0.39218,0.49826,0.36637,0.54513,0.39275,0.47890,0.41609,0.40492,0.44194,0.32768,0.44934,0.24944,0.44284,0.24044,0.46802,0.22677,0.47231,0.13903,0.45128,0.09830,0.39404,0.09357,0.34443,0.13217,0.28955,0.12108,0.23625,0.18074,0.20089,0.14615,0.15153,0.12910,0.12991,0.17221,0.16017,0.21482,0.17884,0.27247,0.20561,0.31959,0.17417,0.38325,0.14200,0.32310,0.09509,0.29403,0.04229,0.27899,0.04008,0.31959,0.07741,0.35117,0.10688,0.39378,0.12358,0.44942,0.15378,0.42694,0.13634,0.49211,0.13290,0.55377,0.16213,0.59487,0.16016,0.61643,0.12701,0.55978,0.07936,0.52670,0.03786,0.53121,0.18755,0.66963,0.22832,0.75335,0.25755,0.87817,0.03649,0.58954,0.08340,0.58904,0.12221,0.61811,0.15487,0.64468,0.18311,0.69080,0.22093,0.78003,0.19415,0.43551,0.21429,0.52824,0.22755,0.61346,0.13658,0.39607,0.25302,0.25429,0.26814,0.32987,0.27647,0.43442,0.27647,0.53456,0.27678,0.64415,0.24426,0.72133,0.27358,0.73455,0.40941,0.16758,0.38010,0.24631,0.35017,0.34519,0.33351,0.43400,0.32024,0.53729,0.31036,0.63176,0.34091,0.62420,0.29987,0.73358,0.29056,0.32631,0.29673,0.23121,0.33962,0.23436,0.23343,0.40108,0.24176,0.45966,0.24669,0.52894],"vertices":[2,11,506.03,1320.82,0.02710,25,664.88,67.57,0.97290,1,25,633.35,151.56,1,2,11,274.33,1300.46,0.15165,25,583.12,285.32,0.84835,2,11,268.14,1140.81,0.17819,25,427.66,248.46,0.82181,3,11,236.11,912.17,0.19788,1,103.64,3067.58,0.00154,25,198.81,217.99,0.80058,3,11,160.46,728.93,0.37551,1,279.55,2976.18,0.06430,25,1.99,241.72,0.56019,3,11,130.83,509.89,0.62334,1,495.16,2927.49,0.17885,25,-216.96,211.51,0.19782,2,11,3.51,265.21,0.61622,1,727.75,2779.24,0.38378,2,11,-196.42,116.79,0.22967,1,858.11,2567.09,0.77033,1,1,904.12,2330.35,1,1,1,1083.04,2330.35,1,2,11,-193.74,-147.26,0.13121,1,1121.38,2546.64,0.86879,2,11,44.36,-228.97,0.60534,1,1223.62,2776.69,0.39466,2,11,78.68,-379.30,0.68840,1,1376.37,2797.71,0.31160,2,11,115,-538.40,0.84289,1,1538.04,2819.97,0.15711,2,11,180.49,-668.89,0.97316,1,1673.77,2873.78,0.02684,1,11,239.31,-786.11,1,1,11,349.37,-768.27,1,1,11,366.71,-635.17,1,2,11,371.40,-492.28,0.99813,1,1514.54,3079.42,0.00187,2,11,335.04,-336.67,0.96533,1,1356.34,3056.82,0.03467,1,11,450.16,-428.19,1,1,11,585.80,-584.97,1,2,11,769.43,-733.09,0.78544,15,-235.37,-213.35,0.21456,2,11,921.29,-932.88,0.39391,15,-4.25,-115.56,0.60609,2,11,1014.12,-1090.79,0.07327,15,171.71,-64.64,0.92673,2,11,1057.66,-1264.06,0.08859,15,350.36,-65.27,0.91141,2,11,1117.96,-1485.63,0.05837,15,579.96,-61.59,0.94163,2,11,1203.01,-1482.69,0.09584,15,598.13,21.55,0.90416,2,11,1223.96,-1266.69,0.09916,15,394,95.23,0.90084,2,11,1177.28,-1003.99,0.39900,15,127.92,114.91,0.60100,2,11,1063.85,-838.81,0.77521,15,-60.17,45.82,0.22479,2,11,928.51,-648.27,0.94360,15,-278.24,-38.24,0.05640,1,11,798.25,-529.04,1,1,11,678.52,-416.14,1,1,11,843.51,-527.78,1,3,11,1025.24,-623.44,0.94050,14,24.54,-341.10,0.05101,15,-278.40,61.63,0.00849,2,11,1215.61,-730.34,0.89054,14,241.03,-312.77,0.10946,2,11,1400.61,-749.48,0.61299,14,400.67,-217.35,0.38702,2,11,1418.82,-716.82,0.55245,14,395.70,-180.29,0.44755,2,11,1461.09,-833.51,0.66588,14,499.42,-248.45,0.33412,2,11,1666.89,-835.92,0.41941,14,665.71,-127.18,0.58059,2,11,1752.82,-727.82,0.54134,14,669.83,10.85,0.45866,2,11,1739.95,-455.20,0.69462,14,496.31,221.52,0.30538,3,11,1629.51,-227.65,0.68243,13,-126.91,-635.69,0.00863,14,271.63,337.67,0.30895,3,11,1632.41,35.07,0.59380,13,73.94,-466.30,0.21078,14,116.67,549.85,0.19542,2,11,1471.49,275.80,0.49354,13,151.15,-187.23,0.50646,2,11,1537.16,450.70,0.41872,13,326.48,-122.74,0.58128,2,11,1556.20,688.45,0.37626,13,518.97,18.11,0.62374,2,11,1446.96,782.20,0.44609,13,518.62,162.07,0.55391,2,11,1360.51,629.90,0.51691,13,346.83,128.08,0.48309,3,11,1234.26,529.55,0.65304,12,-14.78,-313.35,4.7E-04,13,188.38,158.14,0.34650,2,11,1135.86,392.88,0.71810,13,20.62,143.40,0.28190,3,11,974.73,529.06,0.58361,12,-116.12,-74.42,0.33854,13,18.52,354.36,0.07785,3,11,1101.18,694.03,0.40856,12,85.03,-126.80,0.57077,13,226.03,366.34,0.02067,2,11,1149.22,922.58,0.37316,12,314.28,-82.21,0.62684,2,11,1162.17,1176.24,0.29712,12,553.02,4.47,0.70288,2,11,1066.84,1178.43,0.33079,12,517.99,93.15,0.66921,2,11,1008.98,994.82,0.35154,12,326.33,75.08,0.64846,2,11,922.20,846.26,0.44025,12,155.71,97.29,0.55975,2,11,799.79,755.64,0.60407,12,24.63,174.84,0.39593,3,11,864.66,616.92,0.52897,12,-77.96,61.14,0.45097,13,13.16,495.10,0.02006,2,11,705.87,686.35,0.75734,12,-75.71,234.44,0.24266,3,11,561.08,690.07,0.84474,25,72.02,-154.64,0.07727,12,-128.57,369.29,0.07799,2,11,477.70,542.98,0.99455,25,-92.05,-113.77,0.00545,2,11,426.76,547.90,0.94120,25,-100.97,-63.38,0.05880,2,11,544.64,716.82,0.66388,25,93.37,-131.63,0.33612,2,11,601.69,949.68,0.33640,25,333.01,-124.13,0.66360,2,11,573.90,1145.73,0.15277,25,514.42,-44.77,0.84723,3,11,314.48,407.03,0.94393,1,613.69,3101.43,0.04801,25,-266.79,7,0.00807,2,11,136.84,196.46,0.75042,1,807.91,2906.04,0.24958,2,11,-141.19,32.26,0.34738,1,947.14,2614.71,0.65262,2,11,437.71,1140.29,0.04657,25,472.64,84.97,0.95343,2,11,458.43,917.78,0.12731,25,263.84,5.32,0.87269,2,11,407.01,727.69,0.32414,25,66.93,3.87,0.67586,3,11,358.86,567.25,0.60212,1,457.98,3159.67,0.00631,25,-100.55,7.22,0.39157,3,11,263.41,423.79,0.87310,1,592.53,3052.03,0.07994,25,-264.35,60.70,0.04696,2,11,71.72,226.08,0.67856,1,772.71,2843.77,0.32144,3,11,861.58,423.58,0.78160,12,-257.29,-11.17,0.15770,13,-135.26,371.17,0.06070,1,11,654.36,309.06,1,1,11,461.75,228.71,1,3,11,929.25,704.84,0.42993,12,28.16,35.81,0.56719,13,121.93,503.60,0.00288,3,11,1307.45,181.21,0.71460,13,-27.61,-124.77,0.28028,14,-231.11,472.38,0.00513,2,11,1138.03,94.02,0.81308,13,-204.28,-53.42,0.18692,3,11,898.43,33.12,0.99210,13,-406.88,88.26,0.00743,14,-470.09,108.89,4.7E-04,1,11,665.59,12.67,1,2,11,410.92,-11.19,0.99201,1,1038.75,3160.90,0.00799,2,11,217.93,127.35,0.84721,1,883.85,2980.78,0.15279,2,11,199.41,-14.46,0.81682,1,1023.50,2949.91,0.18318,2,11,1574.28,-543.27,0.51790,14,416.33,51.79,0.48210,2,11,1379.01,-420.24,0.49065,14,186.27,33.44,0.50935,2,11,1136.63,-298.40,0.75034,14,-80.82,-14.07,0.24966,2,11,923.20,-237.47,0.93514,14,-288.25,-93.02,0.06486,1,11,677.52,-195.60,1,1,11,453.75,-168.04,1,1,11,484.05,-311.47,1,2,11,212.64,-139.06,0.83276,1,1148.78,2952.18,0.16724,3,11,1155.66,-11.65,0.92113,13,-272.80,-135.78,0.02435,14,-237.24,227.02,0.05452,2,11,1379.35,-21.51,0.87025,14,-52.16,353.04,0.12975,2,11,1389.92,-225.70,0.68916,14,78.54,195.80,0.31084,2,11,957.99,244.20,0.88563,13,-208.14,181.01,0.11437,2,11,825.28,192.70,0.99140,13,-333.81,247.87,0.00860,1,11,666.26,155.12,1]}},"bg_2":{"bg_2":{"type":"mesh","width":32,"height":32,"hull":12,"triangles":[2,3,4,2,4,5,1,2,5,11,1,5,0,1,11,9,10,11,9,6,7,9,11,5,5,6,9,7,8,9],"uvs":[0.17557,0.29042,0.20098,0.27434,0.20257,0.21595,0.11568,0,0.41262,0,0.54771,0.34334,0.80515,0.49386,1,0.84145,1,1,0,1,0,0.54433,0.20138,0.39712],"vertices":[-1651.67,3459.54,-1522.75,3521.32,-1514.69,3745.60,-1955.49,4575.06,-449.13,4575.06,236.19,3256.27,1542.18,2678.16,2530.66,1343.06,2530.66,734.06,-2542.34,734.06,-2542.33,2484.28,-1520.73,3049.73]}},"bg_3":{"bg_3":{"x":2974.15,"y":-47.61,"rotation":-90.33,"width":259,"height":1403}},"bg_4":{"bg_4":{"x":1101.75,"y":-71.99,"rotation":-90.34,"width":1414,"height":2454}},"bg_5":{"bg_5":{"type":"mesh","width":32,"height":32,"hull":10,"triangles":[5,3,4,3,5,7,7,5,6,8,9,1,9,0,1,1,2,8,8,2,7,7,2,3],"uvs":[0.79307,1,0.78339,0.96924,0.78364,0.87353,0.80046,0.79031,0.83817,0.74558,0.88787,0.75078,0.93501,0.78823,0.90647,0.87457,0.87461,0.95467,0.83461,1],"vertices":[2,1,1577.46,2131.26,0.98732,16,-285.34,-194.27,0.01268,2,1,1531.33,2203.05,0.98488,16,-298.20,-109.91,0.01512,2,1,1532.54,2426.43,0.82477,16,-206.04,93.58,0.17523,2,1,1612.67,2620.67,0.56940,16,-53.71,238.29,0.43060,2,1,1792.34,2725.07,0.40248,16,152.92,260.40,0.59752,2,1,2029.07,2712.93,0.14962,16,364.14,152.82,0.85038,2,1,2253.66,2625.53,0.13367,16,533.60,-18.54,0.86633,2,1,2117.69,2424,0.22086,16,327.30,-147.14,0.77914,2,1,1965.94,2237.05,0.58772,16,112.52,-256.01,0.41228,2,1,1775.34,2131.26,0.85065,16,-104.64,-274.93,0.14935]}},"bg_6":{"bg_6":{"x":79.35,"y":2193.50,"scaleX":2,"width":3387,"height":4980}},"bg_7":{"bg_2":{"type":"mesh","width":32,"height":32,"hull":6,"triangles":[1,3,0,2,3,1,5,0,3,5,3,4],"uvs":[0,0,0.20416,0.21947,0.19153,0.28139,0.17665,0.29103,0.19538,0.42394,0,0.50402],"vertices":[-2800.64,3145.73,-2364.44,1729.08,-2093.07,1696.02,-2023.55,1758.27,-1537.77,1448,-808.61,2339.81]}},"bg_8":{"bg_2":{"type":"mesh","width":32,"height":32,"hull":21,"triangles":[12,13,14,23,12,14,12,23,37,11,12,37,29,0,1,20,0,29,22,1,2,29,1,22,22,2,3,29,19,20,28,29,22,28,19,29,36,28,22,46,36,22,3,46,22,28,18,19,27,28,36,27,18,28,35,27,36,35,36,46,45,35,46,17,18,27,26,17,27,53,26,27,53,27,35,34,53,35,45,34,35,44,34,45,25,16,17,25,17,26,51,44,45,53,25,26,52,53,34,52,25,53,33,52,34,33,34,44,24,15,16,25,24,16,43,33,44,43,44,51,50,43,51,52,24,25,54,24,52,23,14,15,52,33,32,52,32,54,32,33,43,24,23,15,23,24,54,37,23,54,37,54,32,42,32,43,42,43,50,49,42,50,31,37,32,31,32,42,11,37,31,45,46,3,45,3,51,51,3,50,50,3,49,3,4,49,41,31,42,41,42,49,10,11,31,30,10,31,47,41,49,41,30,31,48,47,49,4,48,49,38,30,41,38,41,47,38,47,48,9,10,30,9,30,38,39,38,48,8,9,38,8,38,39,40,39,48,7,8,39,7,39,40,21,7,40,6,7,21,5,6,21,48,4,40,40,4,21,5,21,4],"uvs":[0.97265,0.37848,0.98659,0.38076,1,0.38296,1,0.40832,0.99527,0.83125,0.97516,0.79689,0.96809,0.75413,0.95767,0.71284,0.93981,0.67499,0.92548,0.65026,0.92147,0.61892,0.90999,0.59550,0.88936,0.58020,0.86504,0.57413,0.87229,0.54282,0.88874,0.50992,0.91198,0.48339,0.92964,0.46838,0.94342,0.44059,0.95672,0.41503,0.96737,0.39491,0.97882,0.75372,0.98982,0.40414,0.90111,0.55052,0.91318,0.52256,0.92752,0.49760,0.94071,0.47557,0.95689,0.45219,0.97196,0.42283,0.97985,0.40004,0.92890,0.62370,0.93413,0.58251,0.93879,0.54851,0.95212,0.50974,0.96054,0.48417,0.96942,0.45832,0.98058,0.42914,0.91979,0.56176,0.94837,0.64630,0.96620,0.67356,0.98030,0.70659,0.95402,0.60743,0.96159,0.56447,0.97161,0.52460,0.97866,0.49423,0.98794,0.46384,0.98885,0.43508,0.96949,0.62238,0.98254,0.63564,0.98450,0.57318,0.98590,0.52869,0.98681,0.49980,0.94522,0.50746,0.95032,0.48039,0.93007,0.53692],"vertices":[1,1,-1161.93,4397.68,1,1,1,-1091.61,4409.18,1,1,1,-1023.95,4420.24,1,1,1,-996.53,4326.76,1,1,1,-562.28,2761.24,1,1,1,-697.29,2859.16,1,2,1,-777.95,3006.67,0.98909,18,544.13,255.55,0.01091,2,1,-873.32,3143.97,0.86548,18,407.70,158.95,0.13452,2,1,-1001.20,3257.96,0.66320,18,294.87,30.05,0.33680,3,1,-1097.68,3328.63,0.59097,17,345.30,382.15,0.08232,18,225.06,-67.06,0.32671,3,1,-1151.10,3438.43,0.52877,17,256.48,298.36,0.19370,18,115.75,-121.47,0.27753,3,1,-1232.28,3508.34,0.40584,17,214.01,200,0.47192,18,46.57,-203.27,0.12224,3,1,-1349.27,3535.28,0.22197,17,223.26,80.31,0.76285,18,20.69,-320.50,0.01518,2,1,-1474.23,3522.91,0.21848,17,272.39,-35.26,0.78152,2,1,-1472.76,3648.66,0.45629,17,151.95,-71.42,0.54371,3,1,-1428.28,3793.42,0.64560,17,0.51000,-72.21,0.35386,18,-236.72,-401.83,5.4E-04,3,1,-1343.83,3924.38,0.85394,17,-149.70,-30.75,0.13428,18,-368.44,-318.57,0.01178,1,1,-1274.12,4004.93,1,3,1,-1237.06,4127.04,0.97558,17,-375.01,10.61,0.01821,18,-572.06,-213.63,0.00620,1,1,-1199.93,4240.23,1,1,1,-1169.89,4329.61,1,1,1,-726.19,3023.48,1,1,1,-1050.58,4327.64,1,3,1,-1324.14,3661.43,0.45267,17,95.35,66.60,0.50222,18,-105.69,-296.51,0.04510,3,1,-1295.64,3781.74,0.63026,17,-27.97,57.86,0.34017,18,-226.24,-269.09,0.02957,3,1,-1252.80,3894.21,0.80931,17,-148.10,65.14,0.16333,18,-339.09,-227.27,0.02736,3,1,-1212.44,3994.25,0.99105,17,-255.64,73.78,0.00478,18,-439.49,-187.81,0.00418,3,1,-1158.93,4103.50,0.98160,17,-375.88,92.20,0.00976,18,-549.22,-135.29,0.00864,1,1,-1117.32,4233.25,1,1,1,-1103.59,4328.52,1,3,1,-1109.78,3431.40,0.57769,17,250.84,339.89,0.09593,18,122.41,-80.09,0.32638,3,1,-1128.83,3590.72,0.65543,17,104.49,274.11,0.07958,18,-36.73,-100.58,0.26499,3,1,-1142.90,3722.68,0.85656,17,-17.24,221.27,0.05456,18,-168.56,-115.83,0.08888,3,1,-1119.96,3884.61,0.96898,17,-178.63,194.78,0.02438,18,-330.69,-94.35,0.00664,3,1,-1106.59,3990.85,0.96960,17,-284.01,175.80,0.02909,18,-437.05,-81.94,0.00131,3,1,-1091.33,4098.83,0.98582,17,-391.62,158.11,0.00510,18,-545.17,-67.65,0.00908,1,1,-1068.57,4222.30,1,3,1,-1221.09,3646.71,0.61160,17,78.62,169.35,0.23470,18,-91.89,-193.33,0.15370,3,1,-990.56,3375.91,0.73118,17,268.18,470.25,0.00302,18,176.83,39.63,0.26581,2,1,-874.29,3300.92,0.90760,18,250.76,156.57,0.09240,1,1,-769.93,3199.33,1,2,1,-1005.06,3527.26,0.81201,18,25.61,23.76,0.18799,2,1,-1014.68,3696.40,0.94910,18,-143.44,12.62,0.05090,1,1,-1009.03,3857.67,1,1,1,-1007.51,3979.68,1,1,1,-995.18,4104.93,1,1,1,-1021.87,4212.21,1,2,1,-913.58,3494.26,0.93383,18,57.79,115.53,0.06617,1,1,-835.76,3464,1,1,1,-893.72,3697.01,1,1,1,-935,3862.98,1,1,1,-961.81,3970.77,1,3,1,-1155.99,3883.14,0.92118,17,-166.46,160.84,0.06672,18,-328.89,-130.36,0.01211,3,1,-1160.45,3990.18,0.98272,17,-267.28,124.61,0.01414,18,-435.89,-135.79,0.00314,3,1,-1197.91,3752.91,0.77990,17,-29.65,159.74,0.15671,18,-198.29,-171.11,0.06339]}},"bg_9":{"bg_2":{"type":"mesh","width":32,"height":32,"hull":34,"triangles":[20,21,60,13,14,12,60,23,24,23,60,21,20,60,59,21,22,23,2,52,1,33,0,1,52,33,1,32,33,52,49,32,52,50,49,52,52,53,50,2,53,52,31,32,49,46,31,49,53,2,3,51,50,53,4,51,53,3,4,53,50,46,49,47,46,50,47,50,51,30,31,46,5,51,4,48,47,51,45,30,46,45,46,47,5,48,51,29,30,45,44,45,47,44,47,48,6,48,5,34,29,45,34,45,44,43,44,48,43,48,6,34,28,29,40,28,34,27,28,40,35,34,44,35,44,43,40,34,35,37,27,40,7,43,6,41,40,35,56,26,27,56,27,37,25,26,56,60,24,25,60,25,56,36,35,43,36,43,7,41,35,36,41,37,40,38,37,41,8,36,7,61,56,37,61,37,38,42,41,36,38,41,42,59,60,56,59,56,61,9,36,8,42,36,9,55,61,38,39,38,42,55,38,39,19,20,59,58,59,61,58,61,55,19,59,58,10,42,9,39,42,10,54,55,39,18,19,58,11,39,10,54,39,11,57,58,55,57,55,54,17,18,58,17,58,57,12,54,11,15,57,54,14,15,54,16,17,57,16,57,15,12,14,54],"uvs":[0.69455,1.1E-05,0.70986,0,0.81206,0.09357,0.81265,0.11439,0.80544,0.12064,0.80342,0.16018,0.80117,0.20240,0.79710,0.24919,0.79395,0.28189,0.78697,0.31192,0.76951,0.33146,0.75082,0.35584,0.73124,0.38289,0.71323,0.40906,0.69589,0.39419,0.68194,0.38468,0.65695,0.38527,0.63133,0.37189,0.60590,0.34900,0.58451,0.32373,0.57049,0.29992,0.54798,0.28149,0.51849,0.26305,0.55383,0.25354,0.58332,0.24551,0.60854,0.23481,0.62835,0.21994,0.65392,0.21122,0.66653,0.19308,0.68161,0.18327,0.68799,0.14875,0.69204,0.10772,0.69294,0.06640,0.69429,0.02388,0.70431,0.20464,0.73448,0.23568,0.76529,0.27301,0.67605,0.23945,0.70400,0.27636,0.72750,0.31495,0.69066,0.22603,0.71860,0.25203,0.75100,0.29272,0.77381,0.22071,0.74142,0.19680,0.71189,0.16702,0.71506,0.12508,0.74555,0.14857,0.77603,0.17206,0.71824,0.07349,0.75063,0.09992,0.77953,0.11879,0.72046,0.04665,0.78588,0.10117,0.70058,0.33927,0.68152,0.31201,0.63611,0.26000,0.67200,0.35773,0.63960,0.32459,0.61102,0.29397,0.59642,0.27049,0.65678,0.28367],"vertices":[1,1,-544.24,2577.62,1,1,1,-466.59,2577.66,1,1,1,51.88,2218.27,1,1,1,54.86,2138.27,1,1,1,18.32,2114.29,1,2,1,8.04,1962.40,0.94159,6,176.85,387.99,0.05841,2,1,-3.38,1800.24,0.85985,6,165.43,225.83,0.14015,3,1,-24,1620.53,0.77762,6,144.81,46.12,0.22107,7,-545.97,-2.06,0.00132,3,1,-39.99,1494.91,0.72707,6,128.82,-79.50,0.25645,7,-440.72,68.36,0.01648,3,1,-75.39,1379.57,0.70921,6,93.42,-194.84,0.22105,7,-330.48,117.38,0.06974,3,1,-163.99,1304.54,0.67126,6,4.82,-269.87,0.14631,7,-215.72,99.81,0.18243,3,1,-258.78,1210.89,0.60467,6,-89.96,-363.52,0.06933,7,-82.85,89.79,0.32600,3,1,-358.13,1106.97,0.52926,6,-189.32,-467.44,0.02300,7,60.77,83.08,0.44775,3,1,-449.49,1006.48,0.49541,6,-280.68,-567.94,0.00317,7,196.55,80.14,0.50143,3,1,-537.42,1063.58,0.49097,8,-499.14,514.89,0.00434,7,211.21,-23.67,0.50469,3,1,-608.23,1100.12,0.50321,8,-430.21,474.93,0.02167,7,230.13,-101.07,0.47511,3,1,-734.99,1097.84,0.51714,8,-303.48,471,0.06984,7,315.08,-195.19,0.41302,3,1,-864.94,1149.23,0.53879,8,-176.20,413.31,0.15591,7,361.63,-326.95,0.30530,3,1,-993.99,1237.16,0.54790,8,-51.62,319.16,0.27578,7,380.02,-482.02,0.17632,3,1,-1102.48,1334.23,0.53031,8,51.99,216.90,0.39742,7,378.03,-627.59,0.07227,3,1,-1173.59,1425.66,0.50357,8,118.54,122.10,0.47843,7,355.75,-741.25,0.01800,3,1,-1287.79,1496.46,0.48965,8,229.14,45.79,0.50880,7,377.32,-873.88,0.00155,2,1,-1437.39,1567.27,0.50610,8,375.09,-32.26,0.49390,3,1,-1258.10,1603.81,0.52761,5,-721.46,-184.71,0.00363,8,194.22,-59.98,0.46875,3,1,-1108.50,1634.64,0.56185,5,-571.85,-153.87,0.02633,8,43.29,-83.45,0.41183,3,1,-980.59,1675.76,0.59187,5,-443.95,-112.76,0.08416,8,-86.47,-118.25,0.32397,4,1,-880.09,1732.86,0.61466,5,-343.46,-55.66,0.17853,6,-711.28,158.44,0.00104,8,-189.64,-170.36,0.20576,5,1,-750.34,1766.36,0.62728,5,-213.70,-22.15,0.26248,6,-581.52,191.95,0.01373,8,-320.89,-197.47,0.09260,7,-179.12,-645.67,0.00391,5,1,-686.38,1836.02,0.60228,5,-149.74,47.51,0.33167,6,-517.57,261.61,0.03082,8,-388.17,-263.92,0.03507,7,-273.65,-643.17,1.7E-04,4,1,-609.87,1873.71,0.61209,5,-73.23,85.19,0.33709,6,-441.06,299.30,0.03993,8,-466.44,-297.81,0.01089,4,1,-577.53,2006.29,0.69930,5,-40.89,217.78,0.28940,6,-408.72,431.88,0.00798,8,-505.23,-428.66,0.00331,4,1,-556.97,2163.89,0.81921,5,-20.33,375.37,0.17965,6,-388.16,589.48,4.3E-04,8,-533.48,-585.06,7.2E-04,2,1,-552.41,2322.63,0.92576,5,-15.77,534.11,0.07424,1,1,-545.55,2485.93,1,5,1,-494.71,1791.64,0.60947,5,41.93,3.12,0.26062,6,-325.90,217.23,0.12524,8,-577.44,-210.20,0.00450,7,-366.01,-469.45,1.7E-04,5,1,-341.67,1672.42,0.63471,5,194.97,-116.09,0.14408,6,-172.85,98.01,0.21887,8,-724.47,-83.64,0.00192,7,-376.56,-275.74,4.2E-04,5,1,-185.40,1529.04,0.65187,5,351.24,-259.47,0.07913,6,-16.59,-45.37,0.26747,8,-873.53,67.22,9.0E-04,7,-371.01,-63.73,6.3E-04,5,1,-638.09,1657.92,0.67294,5,-101.45,-130.59,0.20144,6,-469.28,83.51,0.03672,8,-427.69,-83.67,0.05778,7,-171.02,-489.81,0.03111,5,1,-496.32,1516.16,0.71460,5,40.32,-272.36,0.11224,6,-327.51,-58.26,0.06828,8,-562.35,64.87,0.03491,7,-157.15,-289.80,0.06997,5,1,-377.11,1367.94,0.73018,5,159.53,-420.57,0.06443,6,-208.29,-206.47,0.08357,8,-674.16,218.74,0.02469,7,-123.62,-102.57,0.09714,5,1,-563.98,1709.48,0.62878,5,-27.34,-79.04,0.26002,6,-395.17,135.06,0.08617,8,-504.23,-131.53,0.02018,7,-258.56,-467.76,0.00485,5,1,-422.22,1609.59,0.67299,5,114.42,-178.92,0.15032,6,-253.40,35.18,0.15323,8,-640.94,-24.83,0.01169,7,-276.29,-295.25,0.01178,5,1,-257.89,1453.33,0.69834,5,278.75,-335.19,0.08796,6,-89.08,-121.09,0.18816,8,-797.41,139.30,0.00822,7,-266.30,-68.71,0.01732,3,1,-142.15,1729.92,0.78948,5,394.49,-58.60,0.05843,6,26.66,155.50,0.15209,3,1,-306.47,1821.74,0.73731,5,230.17,33.23,0.11499,6,-137.66,247.33,0.14770,3,1,-456.30,1936.13,0.71024,5,80.34,147.61,0.15660,6,-287.48,361.71,0.13316,3,1,-440.19,2097.22,0.89590,5,96.45,308.71,0.07981,6,-271.37,522.81,0.02429,3,1,-285.53,2007.01,0.88388,5,251.11,218.49,0.05929,6,-116.72,432.60,0.05683,3,1,-130.87,1916.79,0.85021,5,405.77,128.28,0.03795,6,37.94,342.38,0.11184,1,1,-424.08,2295.38,1,1,1,-259.75,2193.88,1,1,1,-113.15,2121.39,1,1,1,-412.80,2398.48,1,1,1,-80.93,2189.05,1,4,1,-513.67,1274.52,0.65666,5,22.97,-514,0.00687,8,-533.19,305.37,0.08341,7,36.51,-144.25,0.25306,4,1,-610.33,1379.23,0.65418,5,-73.69,-409.29,0.01519,8,-441.77,196.05,0.13274,7,20.98,-285.91,0.19788,4,1,-840.70,1579,0.63747,5,-304.06,-209.52,0.03955,8,-221.45,-14.76,0.26540,7,21.54,-590.83,0.05758,3,1,-658.66,1203.63,0.51850,8,-384.90,369.07,0.22881,7,185.16,-207.08,0.25269,3,1,-822.98,1330.90,0.50962,8,-227.01,233.91,0.30252,7,197.05,-414.58,0.18786,3,1,-967.97,1448.50,0.49125,8,-87.95,109.35,0.41889,7,203.53,-601.16,0.08986,3,1,-1042.08,1538.72,0.47980,8,-18.35,15.61,0.48780,7,184.13,-716.28,0.03240,4,1,-735.85,1488.07,0.64360,5,-199.21,-300.45,0.03078,8,-321.73,81.19,0.21607,7,21.29,-452.04,0.10955]}},"bubble_1":{"bubble_1":{"type":"mesh","width":32,"height":32,"hull":20,"triangles":[20,1,2,0,1,20,22,21,2,21,20,2,22,2,3,23,20,21,3,4,22,18,19,0,20,18,0,23,18,20,4,24,22,17,18,23,26,21,22,23,21,26,5,24,4,26,22,24,25,24,5,28,17,23,28,23,26,16,17,28,5,7,25,30,16,28,7,27,25,26,24,25,27,26,25,5,6,7,8,27,7,29,31,28,26,29,28,30,28,31,27,29,26,33,31,29,31,13,30,32,31,33,10,29,27,10,27,8,30,15,16,32,13,31,30,14,15,13,14,30,12,13,32,10,33,29,11,33,10,32,33,11,12,32,11,9,10,8],"uvs":[0.05006,0.25253,0.32946,0.08276,0.44536,0,1,0,1,0.39833,0.99999,0.44361,1,0.65199,0.87792,0.69593,0.86136,0.75386,0.78271,1,0.58610,0.93561,0.52608,1,0.37499,0.99953,0.31084,0.95958,0.06041,0.88967,0.10594,0.61205,0.27979,0.61205,0.31291,0.51218,0.27565,0.46025,0.15561,0.45426,0.41172,0.34839,0.46480,0.40137,0.69722,0.49498,0.43911,0.42775,0.72760,0.53531,0.77859,0.65624,0.68693,0.52916,0.77865,0.67836,0.35311,0.65544,0.49328,0.84740,0.34281,0.67334,0.43247,0.79866,0.40052,0.87525,0.47370,0.85934],"vertices":[3,33,-1482.79,4260.46,0.86490,35,-2058.70,4250.38,0.06510,34,-2189.86,4055.24,0.07000,3,33,-1382.49,4323.62,0.86490,35,-1958.40,4313.54,0.06510,34,-2089.56,4118.40,0.07000,4,33,-1495.99,4534.66,0.68783,35,-2071.90,4524.58,0.11197,34,-2203.06,4329.44,0.06020,36,-2340.62,4482.99,0.14000,4,33,-1296.88,4534.66,0.68783,35,-1872.79,4524.58,0.11197,34,-2003.95,4329.44,0.06020,36,-2141.50,4482.99,0.14000,4,33,-1296.88,4386.48,0.68783,35,-1872.79,4376.40,0.11197,34,-2003.95,4181.26,0.06020,36,-2141.50,4334.81,0.14000,3,33,-1217.26,4204.98,0.68074,35,-1793.17,4194.90,0.19040,36,-2061.89,4153.32,0.12886,3,33,-1217.26,4127.47,0.68074,35,-1793.17,4117.39,0.19040,36,-2061.89,4075.80,0.12886,3,33,-1261.09,4111.12,0.68074,35,-1837,4101.04,0.19040,36,-2105.71,4059.45,0.12886,3,33,-1649.13,4391.49,0.73543,35,-2225.04,4381.41,0.20020,34,-2356.20,4186.27,0.06437,3,33,-1626.88,4298.29,0.73543,35,-2202.79,4288.21,0.20020,34,-2333.96,4093.07,0.06437,3,33,-1699.84,4283.02,0.73543,35,-2275.75,4272.95,0.20020,34,-2406.91,4077.80,0.06437,4,33,-1826.53,3878.78,0.58211,35,-2402.44,3868.70,0.16796,34,-2533.60,3673.56,0.17993,36,-2671.16,3827.11,0.07000,4,33,-1880.77,3878.96,0.58211,35,-2456.68,3868.88,0.16796,34,-2587.84,3673.74,0.17993,36,-2725.40,3827.29,0.07000,4,33,-2005.61,4060.17,0.68866,35,-2581.52,4050.09,0.12599,34,-2712.68,3854.95,0.05574,36,-2850.24,4008.50,0.12962,4,33,-2095.52,4086.18,0.68866,35,-2671.43,4076.10,0.12599,34,-2802.59,3880.96,0.05574,36,-2940.14,4034.51,0.12962,4,33,-2079.17,4189.45,0.68866,35,-2655.08,4179.38,0.12599,34,-2786.24,3984.23,0.05574,36,-2923.80,4137.79,0.12962,4,33,-2016.76,4189.45,0.68866,35,-2592.67,4179.38,0.12599,34,-2723.83,3984.23,0.05574,36,-2861.38,4137.79,0.12962,3,33,-1864.39,4368.79,0.73543,35,-2440.30,4358.71,0.20020,34,-2571.46,4163.57,0.06437,3,33,-1401.81,4183.19,0.86490,35,-1977.72,4173.11,0.06510,34,-2108.88,3977.97,0.07000,3,33,-1444.90,4185.42,0.86490,35,-2020.81,4175.34,0.06510,34,-2151.97,3980.20,0.07000,3,33,-1352.96,4224.80,0.86490,35,-1928.87,4214.72,0.06510,34,-2060.03,4019.58,0.07000,4,33,-1489.02,4385.35,0.68783,35,-2064.93,4375.27,0.11197,34,-2196.09,4180.13,0.06020,36,-2333.64,4333.68,0.14000,4,33,-1405.58,4350.53,0.68783,35,-1981.49,4340.45,0.11197,34,-2112.65,4145.31,0.06020,36,-2250.20,4298.86,0.14000,3,33,-1841.34,4418.87,0.73543,35,-2417.25,4408.79,0.20020,34,-2548.41,4213.65,0.06437,3,33,-1315.05,4170.87,0.68074,35,-1890.96,4160.79,0.19040,36,-2159.68,4119.21,0.12886,3,33,-1296.75,4125.89,0.68074,35,-1872.66,4115.81,0.19040,36,-2141.37,4074.22,0.12886,3,33,-1745.56,4431.62,0.73543,35,-2321.46,4421.55,0.20020,34,-2452.62,4226.40,0.06437,3,33,-1688.98,4400.58,0.73543,35,-2264.89,4390.50,0.20020,34,-2396.05,4195.36,0.06437,3,33,-1824.86,4330.24,0.73543,35,-2400.77,4320.16,0.20020,34,-2531.93,4125.02,0.06437,3,33,-1745.22,4294.34,0.73543,35,-2321.13,4284.26,0.20020,34,-2452.29,4089.12,0.06437,4,33,-1994.14,4166.65,0.68866,35,-2570.05,4156.57,0.12599,34,-2701.21,3961.43,0.05574,36,-2838.76,4114.98,0.12962,4,33,-1961.95,4120.03,0.68866,35,-2537.86,4109.95,0.12599,34,-2669.02,3914.81,0.05574,36,-2806.57,4068.36,0.12962,4,33,-1871.61,3925.19,0.58211,35,-2447.52,3915.11,0.16796,34,-2578.68,3719.97,0.17993,36,-2716.23,3873.52,0.07000,4,33,-1845.34,3931.11,0.58211,35,-2421.25,3921.03,0.16796,34,-2552.41,3725.89,0.17993,36,-2689.96,3879.44,0.07000]}},"bubble_2":{"bubble_2":{"type":"mesh","width":32,"height":32,"hull":12,"triangles":[13,12,2,3,13,2,1,2,12,11,0,1,11,1,12,4,13,3,16,11,12,14,12,13,16,12,14,10,11,16,13,4,5,14,13,5,15,16,14,15,9,10,15,10,16,8,9,15,8,15,14,5,7,8,5,8,14,6,7,5],"uvs":[0,0.10592,0.33317,0.09097,0.36857,0.08100,0.80401,0.08100,0.87658,0.43811,0.89251,0.53278,0.96508,1,0.31724,1,0.28184,0.74539,0.24467,0.71383,0.12253,0.53278,0.05350,0.45804,0.41990,0.43977,0.45884,0.46302,0.42521,0.49624,0.36945,0.56415,0.31594,0.46627],"vertices":[3,33,260.07,3347.47,0.79980,35,-315.84,3337.40,0.14000,34,-447,3142.25,0.06020,3,33,314.96,3274.40,0.79980,35,-260.95,3264.33,0.14000,34,-392.11,3069.18,0.06020,3,33,479.86,3476.66,0.79980,35,-96.05,3466.59,0.07000,36,-364.76,3424.99,0.13020,3,33,546.29,3575.77,0.79980,35,-29.62,3565.70,0.07000,36,-298.34,3524.10,0.13020,3,33,643.98,3534.23,0.79980,35,68.07,3524.16,0.07000,36,-200.65,3482.56,0.13020,3,33,795.56,3403.59,0.79980,35,219.65,3393.51,0.06020,36,-49.06,3351.92,0.14000,3,33,815.45,3267.16,0.79980,35,239.54,3257.09,0.06020,36,-29.18,3215.50,0.14000,3,33,637.94,3267.16,0.79980,35,62.03,3257.09,0.06020,36,-206.69,3215.50,0.14000,3,33,628.24,3341.51,0.79980,35,52.33,3331.43,0.06020,36,-216.39,3289.84,0.14000,4,33,421.27,3673.21,0.80436,35,-154.64,3663.13,0.06054,34,-285.80,3467.99,0.06510,36,-423.36,3621.54,0.07000,4,33,387.81,3726.07,0.80436,35,-188.11,3716,0.06054,34,-319.27,3520.86,0.06510,36,-456.82,3674.41,0.07000,3,33,183.24,3277.59,0.79980,35,-392.67,3267.52,0.14000,34,-523.83,3072.37,0.06020,3,33,244.05,3197.53,0.79980,35,-331.86,3187.45,0.14000,34,-463.02,2992.31,0.06020,3,33,586.30,3435.10,0.79980,35,10.39,3425.03,0.07000,36,-258.33,3383.44,0.13020,3,33,667.52,3414.26,0.79980,35,91.61,3404.18,0.06020,36,-177.10,3362.59,0.14000,4,33,455.46,3716.92,0.80436,35,-120.45,3706.84,0.06054,34,-251.61,3511.70,0.06510,36,-389.17,3665.25,0.07000,4,33,440.80,3745.50,0.80436,35,-135.11,3735.42,0.06054,34,-266.27,3540.28,0.06510,36,-403.83,3693.83,0.07000]}},"bubble_3":{"bubble_2":{"type":"mesh","width":32,"height":32,"hull":12,"triangles":[13,12,2,3,13,2,1,2,12,11,0,1,11,1,12,4,13,3,16,11,12,14,12,13,16,12,14,10,11,16,13,4,5,14,13,5,15,16,14,15,9,10,15,10,16,8,9,15,8,15,14,5,7,8,5,8,14,6,7,5],"uvs":[0,0.10592,0.33317,0.09097,0.36857,0.08100,0.80401,0.08100,0.87658,0.43811,0.89251,0.53278,0.96508,1,0.31724,1,0.28184,0.74539,0.24467,0.71383,0.12253,0.53278,0.05350,0.45804,0.41990,0.43977,0.45884,0.46302,0.42521,0.49624,0.36945,0.56415,0.31594,0.46627],"vertices":[3,33,2154.81,2913.82,0.79980,35,1578.90,2903.74,0.14000,34,1447.74,2708.60,0.06020,3,33,2246.10,2918.19,0.79980,35,1670.19,2908.11,0.14000,34,1539.03,2712.97,0.06020,3,33,2622.09,3300.85,0.79980,35,2046.18,3290.77,0.07000,36,1777.46,3249.18,0.13020,3,33,2741.39,3300.85,0.79980,35,2165.48,3290.77,0.07000,36,1896.77,3249.18,0.13020,3,33,2761.28,3196.57,0.79980,35,2185.37,3186.49,0.07000,36,1916.65,3144.91,0.13020,3,33,2733.57,2869.91,0.79980,35,2157.66,2859.83,0.06020,36,1888.95,2818.24,0.14000,3,33,2753.46,2733.48,0.79980,35,2177.55,2723.40,0.06020,36,1908.83,2681.82,0.14000,3,33,2575.95,2733.48,0.79980,35,2000.04,2723.40,0.06020,36,1731.32,2681.82,0.14000,3,33,2566.25,2807.83,0.79980,35,1990.34,2797.75,0.06020,36,1721.62,2756.16,0.14000,4,33,2412.96,2893.35,0.80436,35,1837.05,2883.27,0.06054,34,1705.89,2688.13,0.06510,36,1568.34,2841.68,0.07000,4,33,2379.50,2946.21,0.80436,35,1803.59,2936.13,0.06054,34,1672.43,2740.99,0.06510,36,1534.87,2894.54,0.07000,3,33,2169.47,2811,0.79980,35,1593.56,2800.92,0.14000,34,1462.40,2605.78,0.06020,3,33,2269.86,2816.34,0.79980,35,1693.95,2806.26,0.14000,34,1562.79,2611.12,0.06020,3,33,2646.82,3189.30,0.79980,35,2070.91,3179.22,0.07000,36,1802.19,3137.63,0.13020,3,33,2605.54,2880.58,0.79980,35,2029.63,2870.50,0.06020,36,1760.91,2828.91,0.14000,4,33,2447.15,2937.05,0.80436,35,1871.24,2926.97,0.06054,34,1740.08,2731.83,0.06510,36,1602.53,2885.38,0.07000,4,33,2432.49,2965.63,0.80436,35,1856.58,2955.55,0.06054,34,1725.42,2760.41,0.06510,36,1587.86,2913.97,0.07000]}},"bubble_4":{"bubble_1":{"type":"mesh","width":32,"height":32,"hull":20,"triangles":[20,1,2,0,1,20,22,21,2,21,20,2,22,2,3,23,20,21,3,4,22,18,19,0,20,18,0,23,18,20,4,24,22,17,18,23,26,21,22,23,21,26,5,24,4,26,22,24,25,24,5,28,17,23,28,23,26,16,17,28,5,7,25,30,16,28,7,27,25,26,24,25,27,26,25,5,6,7,8,27,7,29,31,28,26,29,28,30,28,31,27,29,26,33,31,29,31,13,30,32,31,33,10,29,27,10,27,8,30,15,16,32,13,31,30,14,15,13,14,30,12,13,32,10,33,29,11,33,10,32,33,11,12,32,11,9,10,8],"uvs":[0.05006,0.25253,0.32946,0.08276,0.44536,0,1,0,1,0.39833,0.99999,0.44361,1,0.65199,0.87792,0.69593,0.86136,0.75386,0.78271,1,0.58610,0.93561,0.52608,1,0.37499,0.99953,0.31084,0.95958,0.06041,0.88967,0.10594,0.61205,0.27979,0.61205,0.31291,0.51218,0.27565,0.46025,0.15561,0.45426,0.41172,0.34839,0.46480,0.40137,0.69722,0.49498,0.43911,0.42775,0.72760,0.53531,0.77859,0.65624,0.68693,0.52916,0.77865,0.67836,0.35311,0.65544,0.49328,0.84740,0.34281,0.67334,0.43247,0.79866,0.40052,0.87525,0.47370,0.85934],"vertices":[3,33,119.34,5009.75,0.86490,35,-456.57,4999.67,0.06510,34,-587.73,4804.53,0.07000,3,33,219.65,5072.91,0.86490,35,-356.26,5062.83,0.06510,34,-487.42,4867.69,0.07000,4,33,412.86,5072.98,0.68783,35,-163.05,5062.90,0.11197,34,-294.21,4867.76,0.06020,36,-431.77,5021.32,0.14000,4,33,611.97,5072.98,0.68783,35,36.06,5062.90,0.11197,34,-95.10,4867.76,0.06020,36,-232.65,5021.32,0.14000,4,33,611.97,4924.80,0.68783,35,36.06,4914.72,0.11197,34,-95.10,4719.58,0.06020,36,-232.65,4873.14,0.14000,3,33,906.91,4874.19,0.68074,35,331,4864.11,0.19040,36,62.28,4822.52,0.12886,3,33,906.91,4796.67,0.68074,35,331,4786.59,0.19040,36,62.29,4745,0.12886,3,33,863.09,4780.33,0.68074,35,287.18,4770.25,0.19040,36,18.46,4728.66,0.12886,3,33,707.11,4739.02,0.73543,35,131.20,4728.94,0.20020,34,0.04000,4533.80,0.06437,3,33,678.88,4647.45,0.73543,35,102.97,4637.37,0.20020,34,-28.19,4442.23,0.06437,3,33,608.29,4671.40,0.73543,35,32.38,4661.32,0.20020,34,-98.78,4466.18,0.06437,4,33,565.74,4531.10,0.58211,35,-10.17,4521.02,0.16796,34,-141.33,4325.88,0.17993,36,-278.89,4479.43,0.07000,4,33,511.50,4531.28,0.58211,35,-64.41,4521.20,0.16796,34,-195.57,4326.06,0.17993,36,-333.13,4479.61,0.07000,4,33,386.66,4564.72,0.68866,35,-189.25,4554.64,0.12599,34,-320.41,4359.50,0.05574,36,-457.97,4513.05,0.12962,4,33,296.75,4590.73,0.68866,35,-279.16,4580.64,0.12599,34,-410.32,4385.51,0.05574,36,-547.87,4539.06,0.12962,4,33,313.10,4694,0.68866,35,-262.81,4683.92,0.12599,34,-393.97,4488.78,0.05574,36,-531.53,4642.33,0.12962,4,33,375.51,4694,0.68866,35,-200.40,4683.92,0.12599,34,-331.56,4488.78,0.05574,36,-469.11,4642.33,0.12962,3,33,510.22,4828.92,0.73543,35,-65.69,4818.84,0.20020,34,-196.85,4623.70,0.06437,3,33,200.33,4932.48,0.86490,35,-375.58,4922.40,0.06510,34,-506.74,4727.26,0.07000,3,33,157.24,4934.71,0.86490,35,-418.68,4924.63,0.06510,34,-549.84,4729.49,0.07000,3,33,249.18,4974.09,0.86490,35,-326.73,4964.01,0.06510,34,-457.89,4768.88,0.07000,4,33,419.84,4923.67,0.68783,35,-156.07,4913.59,0.11197,34,-287.23,4718.45,0.06020,36,-424.79,4872.01,0.14000,4,33,503.28,4888.85,0.68783,35,-72.64,4878.77,0.11197,34,-203.80,4683.63,0.06020,36,-341.35,4837.19,0.14000,3,33,555.53,4860.33,0.73543,35,-20.38,4850.25,0.20020,34,-151.54,4655.11,0.06437,3,33,809.12,4840.08,0.68074,35,233.21,4830,0.19040,36,-35.50,4788.41,0.12886,3,33,827.43,4795.09,0.68074,35,251.52,4785.01,0.19040,36,-17.20,4743.42,0.12886,3,33,644.49,4822.60,0.73543,35,68.58,4812.52,0.20020,34,-62.58,4617.38,0.06437,3,33,677.42,4767.10,0.73543,35,101.51,4757.02,0.20020,34,-29.65,4561.88,0.06437,3,33,524.65,4775.63,0.73543,35,-51.26,4765.55,0.20020,34,-182.42,4570.41,0.06437,3,33,574.97,4704.22,0.73543,35,-0.94000,4694.14,0.20020,34,-132.10,4499,0.06437,4,33,398.14,4671.20,0.68866,35,-177.77,4661.12,0.12599,34,-308.94,4465.98,0.05574,36,-446.49,4619.53,0.12962,4,33,430.33,4624.58,0.68866,35,-145.58,4614.50,0.12599,34,-276.75,4419.36,0.05574,36,-414.30,4572.91,0.12962,4,33,520.66,4577.51,0.58211,35,-55.25,4567.43,0.16796,34,-186.41,4372.29,0.17993,36,-323.96,4525.84,0.07000,4,33,546.93,4583.43,0.58211,35,-28.98,4573.35,0.16796,34,-160.14,4378.21,0.17993,36,-297.69,4531.76,0.07000]}},"fx_1":{"fx_1":{"scaleX":2.12,"scaleY":2.12,"width":143,"height":143}},"fx_2":{"fx_1":{"scaleX":0.80053,"scaleY":0.80053,"width":143,"height":143}},"fx_3":{"fx_1":{"scaleX":3.89,"scaleY":3.89,"width":143,"height":143}},"fx_4":{"fx_1":{"scaleX":0.99157,"scaleY":0.99157,"width":143,"height":143}},"fx_5":{"fx_1":{"scaleX":0.71291,"scaleY":0.71291,"width":143,"height":143}},"fx_6":{"fx_1":{"scaleX":7.99,"scaleY":7.99,"width":143,"height":143}},"pin_light_1":{"pin_light_1":{"x":-1248.87,"y":3480.16,"scaleX":0.59972,"scaleY":0.59972,"width":440,"height":433}},"pin_light_2":{"pin_light_1":{"x":-33.33,"y":5106.56,"scaleX":1.65,"scaleY":1.65,"width":440,"height":433}},"pin_light_3":{"pin_light_1":{"x":480.26,"y":4051.36,"scaleX":1.02,"scaleY":1.02,"width":440,"height":433}},"pin_light_4":{"pin_light_1":{"x":2596.46,"y":3755.09,"scaleX":0.74234,"scaleY":0.74234,"width":440,"height":433}},"pin_light_5":{"pin_light_1":{"x":-1899.78,"y":3491.17,"scaleX":0.74234,"scaleY":0.74234,"width":440,"height":433}}}},"animations":{"IDLE":{"slots":{"bubble_1":{"color":[{"time":0,"color":"ffffffff","curve":[0.25000,0,0.75000,1]},{"time":2.50,"color":"ffffff68","curve":[0.25000,0,0.75000,1]},{"time":5,"color":"ffffffff","curve":[0.25000,0,0.75000,1]},{"time":7.50,"color":"ffffff68","curve":[0.25000,0,0.75000,1]},{"time":10,"color":"ffffffff"}]},"bubble_2":{"color":[{"time":0,"color":"ffffffc7","curve":[0.38144,0.54545,0.74227,1]},{"time":1,"color":"ffffffff","curve":[0.25000,0,0.75000,1]},{"time":3.50,"color":"ffffff68","curve":[0.25000,0,0.75000,1]},{"time":6,"color":"ffffffff","curve":[0.25000,0,0.75000,1]},{"time":8.50,"color":"ffffff68","curve":[0.24510,0,0.63725,0.55556]},{"time":10,"color":"ffffffc7"}]},"bubble_3":{"color":[{"time":0,"color":"ffffffc7","curve":[0.36275,0.44444,0.75490,1]},{"time":1.50,"color":"ffffff68","curve":[0.25000,0,0.75000,1]},{"time":4,"color":"ffffffff","curve":[0.25000,0,0.75000,1]},{"time":6.50,"color":"ffffff68","curve":[0.25000,0,0.75000,1]},{"time":9,"color":"ffffffff","curve":[0.25773,0,0.61856,0.45455]},{"time":10,"color":"ffffffc7"}]},"bubble_4":{"color":[{"time":0,"color":"ffffff7c","curve":[0.32039,0.28571,0.75728,1]},{"time":2,"color":"ffffffff","curve":[0.25000,0,0.75000,1]},{"time":4.50,"color":"ffffff68","curve":[0.25000,0,0.75000,1]},{"time":7,"color":"ffffffff","curve":[0.25000,0,0.75000,1]},{"time":9.50,"color":"ffffff68","curve":[0.28409,0,0.62500,0.38462]},{"time":10,"color":"ffffff7c"}]},"fx_1":{"color":[{"time":0,"color":"3d75bb00","curve":"stepped"},{"time":2.67,"color":"3d75bb00"},{"time":3.67,"color":"3e75bbff","curve":"stepped"},{"time":4.53,"color":"3e75bbff"},{"time":4.60,"color":"c4a25571"},{"time":4.67,"color":"3e75bbff"},{"time":4.83,"color":"3d75bbbf"},{"time":4.90,"color":"95937946"},{"time":5,"color":"808c87bd"},{"time":5.33,"color":"3d75bb00"}]},"fx_2":{"color":[{"time":0,"color":"3d75bb00","curve":"stepped"},{"time":2.67,"color":"3d75bb00"},{"time":3.67,"color":"ffffffff","curve":"stepped"},{"time":4.53,"color":"ffffffff"},{"time":4.60,"color":"c4a25571"},{"time":4.67,"color":"ffffffff"},{"time":4.83,"color":"cedceebf"},{"time":4.90,"color":"95937946"},{"time":5,"color":"808c87bd"},{"time":5.33,"color":"3d75bb00"}]},"fx_3":{"color":[{"time":0,"color":"3d75bb00","curve":"stepped"},{"time":2.67,"color":"3d75bb00"},{"time":3.67,"color":"97dd5bff","curve":"stepped"},{"time":4.53,"color":"97dd5bff"},{"time":4.60,"color":"c4a25571"},{"time":4.67,"color":"97dd5bff"},{"time":4.83,"color":"80c373bf"},{"time":4.90,"color":"95937946"},{"time":5,"color":"808c87bd"},{"time":5.33,"color":"3d75bb00"}]},"fx_4":{"color":[{"time":0,"color":"3d75bb00","curve":"stepped"},{"time":2.67,"color":"3d75bb00"},{"time":3.67,"color":"285ab0ff","curve":"stepped"},{"time":4.53,"color":"285ab0ff"},{"time":4.60,"color":"c4a25571"},{"time":4.67,"color":"285ab0ff"},{"time":4.83,"color":"2d60b2bf"},{"time":4.90,"color":"95937946"},{"time":5,"color":"808c87bd"},{"time":5.33,"color":"3d75bb00"}]},"fx_5":{"color":[{"time":0,"color":"3d75bb00","curve":"stepped"},{"time":2.67,"color":"3d75bb00"},{"time":3.67,"color":"ffffffff","curve":"stepped"},{"time":4.53,"color":"ffffffff"},{"time":4.60,"color":"c4a25571"},{"time":4.67,"color":"ffffffff"},{"time":4.83,"color":"cedceebf"},{"time":4.90,"color":"95937946"},{"time":5,"color":"808c87bd"},{"time":5.33,"color":"3d75bb00"}]},"fx_6":{"color":[{"time":0,"color":"3d75bb00","curve":"stepped"},{"time":2.67,"color":"3d75bb00"},{"time":3.67,"color":"c4a355ff","curve":"stepped"},{"time":4.53,"color":"c4a355ff"},{"time":4.60,"color":"c4a25571"},{"time":4.67,"color":"c4a355ff"},{"time":4.83,"color":"a2976ebf"},{"time":4.90,"color":"95937946"},{"time":5,"color":"808c87bd"},{"time":5.33,"color":"3d75bb00"}]},"pin_light_1":{"color":[{"time":0,"color":"ffffff00","curve":"stepped"},{"time":1.27,"color":"ffffff00"},{"time":1.77,"color":"ffffffff","curve":"stepped"},{"time":2.27,"color":"ffffffff"},{"time":2.77,"color":"ffffff00","curve":"stepped"},{"time":3.27,"color":"ffffff00"},{"time":3.77,"color":"ffffffff","curve":"stepped"},{"time":4.27,"color":"ffffffff"},{"time":4.77,"color":"ffffff00","curve":"stepped"},{"time":6.27,"color":"ffffff00"},{"time":6.77,"color":"ffffffff","curve":"stepped"},{"time":7.27,"color":"ffffffff"},{"time":7.77,"color":"ffffff00","curve":"stepped"},{"time":8.27,"color":"ffffff00"},{"time":8.77,"color":"ffffffff","curve":"stepped"},{"time":9.27,"color":"ffffffff"},{"time":9.77,"color":"ffffff00"}]},"pin_light_2":{"color":[{"time":0.30000,"color":"ffffffff"},{"time":0.80000,"color":"ffffff00","curve":"stepped"},{"time":2.30,"color":"ffffff00"},{"time":2.80,"color":"ffffffff","curve":"stepped"},{"time":3.30,"color":"ffffffff"},{"time":3.80,"color":"ffffff00","curve":"stepped"},{"time":4.30,"color":"ffffff00"},{"time":4.80,"color":"ffffffff","curve":"stepped"},{"time":5.30,"color":"ffffffff"},{"time":5.80,"color":"ffffff00","curve":"stepped"},{"time":7.30,"color":"ffffff00"},{"time":7.80,"color":"ffffffff","curve":"stepped"},{"time":8.30,"color":"ffffffff"},{"time":8.80,"color":"ffffff00","curve":"stepped"},{"time":9.30,"color":"ffffff00"},{"time":9.80,"color":"ffffffff"}]},"pin_light_3":{"color":[{"time":0.06667,"color":"ffffffff"},{"time":0.56667,"color":"ffffff00","curve":"stepped"},{"time":1.07,"color":"ffffff00"},{"time":1.57,"color":"ffffffff","curve":"stepped"},{"time":2.07,"color":"ffffffff"},{"time":2.57,"color":"ffffff00","curve":"stepped"},{"time":4.07,"color":"ffffff00"},{"time":4.57,"color":"ffffffff","curve":"stepped"},{"time":5.07,"color":"ffffffff"},{"time":5.57,"color":"ffffff00","curve":"stepped"},{"time":6.07,"color":"ffffff00"},{"time":6.57,"color":"ffffffff","curve":"stepped"},{"time":7.07,"color":"ffffffff"},{"time":7.57,"color":"ffffff00","curve":"stepped"},{"time":9.07,"color":"ffffff00"},{"time":9.57,"color":"ffffffff"}]},"pin_light_4":{"color":[{"time":0,"color":"ffffffbb"},{"time":0.36667,"color":"ffffff00","curve":"stepped"},{"time":0.86667,"color":"ffffff00"},{"time":1.37,"color":"ffffffff","curve":"stepped"},{"time":1.87,"color":"ffffffff"},{"time":2.37,"color":"ffffff00","curve":"stepped"},{"time":3.87,"color":"ffffff00"},{"time":4.37,"color":"ffffffff","curve":"stepped"},{"time":4.87,"color":"ffffffff"},{"time":5.37,"color":"ffffff00","curve":"stepped"},{"time":5.87,"color":"ffffff00"},{"time":6.37,"color":"ffffffff","curve":"stepped"},{"time":6.87,"color":"ffffffff"},{"time":7.37,"color":"ffffff00","curve":"stepped"},{"time":8.87,"color":"ffffff00"},{"time":9.37,"color":"ffffffff","curve":"stepped"},{"time":9.87,"color":"ffffffff"},{"time":10,"color":"ffffffbb"}]},"pin_light_5":{"color":[{"time":0,"color":"ffffff00"},{"time":0.50000,"color":"ffffffff","curve":"stepped"},{"time":1,"color":"ffffffff"},{"time":1.50,"color":"ffffff00","curve":"stepped"},{"time":3,"color":"ffffff00"},{"time":3.50,"color":"ffffffff","curve":"stepped"},{"time":4,"color":"ffffffff"},{"time":4.50,"color":"ffffff00","curve":"stepped"},{"time":5,"color":"ffffff00"},{"time":5.50,"color":"ffffffff","curve":"stepped"},{"time":6,"color":"ffffffff"},{"time":6.50,"color":"ffffff00","curve":"stepped"},{"time":8,"color":"ffffff00"},{"time":8.50,"color":"ffffffff","curve":"stepped"},{"time":9,"color":"ffffffff"},{"time":9.50,"color":"ffffff00"}]}},"bones":{"bone180":{"rotate":[{"time":0,"angle":6.21,"curve":[0.25000,0,0.75000,1]},{"time":2.50,"angle":-9.79,"curve":[0.25000,0,0.75000,1]},{"time":5,"angle":6.21,"curve":[0.25000,0,0.75000,1]},{"time":7.50,"angle":-9.79,"curve":[0.25000,0,0.75000,1]},{"time":10,"angle":6.21}],"translate":[{"time":0,"x":-4.38,"y":2.50,"curve":[0.32039,0.28571,0.75728,1]},{"time":2,"x":-3.67,"y":28.27,"curve":[0.25000,0,0.75000,1]},{"time":4.50,"x":-4.48,"y":-1.36,"curve":[0.28409,0,0.62500,0.38462]},{"time":5,"x":-4.38,"y":2.50,"curve":[0.32039,0.28571,0.75728,1]},{"time":7,"x":-3.67,"y":28.27,"curve":[0.25000,0,0.75000,1]},{"time":9.50,"x":-4.48,"y":-1.36,"curve":[0.28409,0,0.62500,0.38462]},{"time":10,"x":-4.38,"y":2.50}]},"bone181":{"rotate":[{"time":0,"angle":-3.05,"curve":[0.33333,0.33333,0.68018,0.70833]},{"time":0.76667,"angle":0.77950,"curve":[0.38172,0.58333,0.73118,1]},{"time":1.50,"angle":3.18,"curve":[0.25000,0,0.75000,1]},{"time":4,"angle":-6.72,"curve":[0.25773,0,0.61856,0.45455]},{"time":5,"angle":-3.05,"curve":[0.33333,0.33333,0.68018,0.70833]},{"time":5.77,"angle":0.77950,"curve":[0.38172,0.58333,0.73118,1]},{"time":6.50,"angle":3.18,"curve":[0.25000,0,0.75000,1]},{"time":9,"angle":-6.72,"curve":[0.25773,0,0.61856,0.45455]},{"time":10,"angle":-3.05}],"translate":[{"time":0,"x":7.57,"y":0.30524,"curve":[0.38172,0.58333,0.73118,1]},{"time":0.76667,"x":8.11,"y":-10.60,"curve":[0.25000,0,0.75000,1]},{"time":3.27,"x":5.89,"y":34.43,"curve":[0.24272,0,0.65534,0.62500]},{"time":5,"x":7.57,"y":0.30524,"curve":[0.38172,0.58333,0.73118,1]},{"time":5.77,"x":8.11,"y":-10.60,"curve":[0.25000,0,0.75000,1]},{"time":8.27,"x":5.89,"y":34.43,"curve":[0.24272,0,0.65534,0.62500]},{"time":10,"x":7.57,"y":0.30524}]},"bone182":{"rotate":[{"time":0,"angle":-11.16,"curve":[0.32039,0.28571,0.75728,1]},{"time":2,"angle":0,"curve":[0.25000,0,0.75000,1]},{"time":4.50,"angle":-12.82,"curve":[0.28409,0,0.62500,0.38462]},{"time":5,"angle":-11.16,"curve":[0.32039,0.28571,0.75728,1]},{"time":7,"angle":0,"curve":[0.25000,0,0.75000,1]},{"time":9.50,"angle":-12.82,"curve":[0.28409,0,0.62500,0.38462]},{"time":10,"angle":-11.16}],"translate":[{"time":0,"x":-13.62,"y":13.62,"curve":[0.37500,0.50000,0.75000,1]},{"time":1.27,"x":0,"y":0,"curve":[0.25000,0,0.75000,1]},{"time":3.77,"x":-27.25,"y":27.25,"curve":[0.25000,0,0.62500,0.50000]},{"time":5,"x":-13.62,"y":13.62,"curve":[0.37500,0.50000,0.75000,1]},{"time":6.27,"x":0,"y":0,"curve":[0.25000,0,0.75000,1]},{"time":8.77,"x":-27.25,"y":27.25,"curve":[0.25000,0,0.62500,0.50000]},{"time":10,"x":-13.62,"y":13.62}]},"bone183":{"rotate":[{"time":0,"angle":-11.67,"curve":[0.36275,0.44444,0.75490,1]},{"time":1.50,"angle":0,"curve":[0.25000,0,0.75000,1]},{"time":4,"angle":-18.46,"curve":[0.25773,0,0.61856,0.45455]},{"time":5,"angle":-11.67,"curve":[0.36275,0.44444,0.75490,1]},{"time":6.50,"angle":0,"curve":[0.25000,0,0.75000,1]},{"time":9,"angle":-18.46,"curve":[0.25773,0,0.61856,0.45455]},{"time":10,"angle":-11.67}],"translate":[{"time":0,"x":-12.39,"y":7.01,"curve":[0.38172,0.58333,0.73118,1]},{"time":0.76667,"x":0,"y":0,"curve":[0.25000,0,0.75000,1]},{"time":3.27,"x":-51.17,"y":28.95,"curve":[0.24272,0,0.65534,0.62500]},{"time":5,"x":-12.39,"y":7.01,"curve":[0.38172,0.58333,0.73118,1]},{"time":5.77,"x":0,"y":0,"curve":[0.25000,0,0.75000,1]},{"time":8.27,"x":-51.17,"y":28.95,"curve":[0.24272,0,0.65534,0.62500]},{"time":10,"x":-12.39,"y":7.01}]},"bone184":{"rotate":[{"time":0,"angle":-9.69,"curve":[0.38172,0.58333,0.73118,1]},{"time":0.76667,"angle":-9.14,"curve":[0.25000,0,0.75000,1]},{"time":3.27,"angle":-11.40,"curve":[0.24272,0,0.65534,0.62500]},{"time":5,"angle":-9.69,"curve":[0.38172,0.58333,0.73118,1]},{"time":5.77,"angle":-9.14,"curve":[0.25000,0,0.75000,1]},{"time":8.27,"angle":-11.40,"curve":[0.24272,0,0.65534,0.62500]},{"time":10,"angle":-9.69}],"translate":[{"time":0,"x":0,"y":0,"curve":[0.25000,0,0.75000,1]},{"time":2.50,"x":-31.14,"y":19.30,"curve":[0.25000,0,0.75000,1]},{"time":5,"x":0,"y":0,"curve":[0.25000,0,0.75000,1]},{"time":7.50,"x":-31.14,"y":19.30,"curve":[0.25000,0,0.75000,1]},{"time":10,"x":0,"y":0}]},"bone185":{"rotate":[{"time":0,"angle":-11.28,"curve":[0.25000,0,0.75000,1]},{"time":2.50,"angle":5.96,"curve":[0.25000,0,0.75000,1]},{"time":5,"angle":-11.28,"curve":[0.25000,0,0.75000,1]},{"time":7.50,"angle":5.96,"curve":[0.25000,0,0.75000,1]},{"time":10,"angle":-11.28}],"translate":[{"time":0,"x":-17.03,"y":14.48,"curve":[0.37500,0.50000,0.75000,1]},{"time":1.27,"x":0,"y":0,"curve":[0.25000,0,0.75000,1]},{"time":3.77,"x":-34.06,"y":28.95,"curve":[0.25000,0,0.62500,0.50000]},{"time":5,"x":-17.03,"y":14.48,"curve":[0.37500,0.50000,0.75000,1]},{"time":6.27,"x":0,"y":0,"curve":[0.25000,0,0.75000,1]},{"time":8.77,"x":-34.06,"y":28.95,"curve":[0.25000,0,0.62500,0.50000]},{"time":10,"x":-17.03,"y":14.48}]},"bone186":{"rotate":[{"time":0,"angle":2.17,"curve":[0.38172,0.58333,0.73118,1]},{"time":0.76667,"angle":0,"curve":[0.25000,0,0.75000,1]},{"time":3.27,"angle":9.00,"curve":[0.25000,0,0.62500,0.50000]},{"time":4.50,"angle":4.50,"curve":[0.33937,0.35211,0.67873,0.70423]},{"time":5,"angle":2.17,"curve":[0.38172,0.58333,0.73118,1]},{"time":5.77,"angle":0,"curve":[0.25000,0,0.75000,1]},{"time":8.27,"angle":9.00,"curve":[0.25000,0,0.62500,0.50000]},{"time":9.50,"angle":4.50,"curve":[0.33937,0.35211,0.67873,0.70423]},{"time":10,"angle":2.17}],"translate":[{"time":0,"x":-2.31,"y":-6.17,"curve":[0.32039,0.28571,0.75728,1]},{"time":2,"x":-17.79,"y":-47.44,"curve":[0.25000,0,0.75000,1]},{"time":4.50,"x":0,"y":0,"curve":[0.28409,0,0.62500,0.38462]},{"time":5,"x":-2.31,"y":-6.17,"curve":[0.32039,0.28571,0.75728,1]},{"time":7,"x":-17.79,"y":-47.44,"curve":[0.25000,0,0.75000,1]},{"time":9.50,"x":0,"y":0,"curve":[0.28409,0,0.62500,0.38462]},{"time":10,"x":-2.31,"y":-6.17}]},"bone187":{"rotate":[{"time":0,"angle":4.63,"curve":[0.37500,0.50000,0.75000,1]},{"time":1.27,"angle":0,"curve":[0.25000,0,0.75000,1]},{"time":3.77,"angle":9.25,"curve":[0.25000,0,0.62500,0.50000]},{"time":5,"angle":4.63,"curve":[0.37500,0.50000,0.75000,1]},{"time":6.27,"angle":0,"curve":[0.25000,0,0.75000,1]},{"time":8.77,"angle":9.25,"curve":[0.25000,0,0.62500,0.50000]},{"time":10,"angle":4.63}],"translate":[{"time":0,"x":0,"y":0,"curve":[0.25000,0,0.75000,1]},{"time":2.50,"x":-23.72,"y":-32.61,"curve":[0.25000,0,0.75000,1]},{"time":5,"x":0,"y":0,"curve":[0.25000,0,0.75000,1]},{"time":7.50,"x":-23.72,"y":-32.61,"curve":[0.25000,0,0.75000,1]},{"time":10,"x":0,"y":0}]},"bone188":{"rotate":[{"time":0,"angle":0,"curve":[0.25000,0,0.75000,1]},{"time":2.50,"angle":-1.86,"curve":[0.25000,0,0.75000,1]},{"time":5,"angle":0,"curve":[0.25000,0,0.75000,1]},{"time":7.50,"angle":-1.86,"curve":[0.25000,0,0.75000,1]},{"time":10,"angle":0}]},"bone189":{"rotate":[{"time":0,"angle":5.42,"curve":[0.37500,0.50000,0.75000,1]},{"time":1.27,"angle":-0.10002,"curve":[0.25000,0,0.75000,1]},{"time":3.77,"angle":10.94,"curve":[0.25000,0,0.62500,0.50000]},{"time":5,"angle":5.42,"curve":[0.37500,0.50000,0.75000,1]},{"time":6.27,"angle":-0.10002,"curve":[0.25000,0,0.75000,1]},{"time":8.77,"angle":10.94,"curve":[0.25000,0,0.62500,0.50000]},{"time":10,"angle":5.42}],"translate":[{"time":0,"x":0,"y":0,"curve":[0.25000,0,0.75000,1]},{"time":2.50,"x":-58.32,"y":8.77,"curve":[0.25000,0,0.75000,1]},{"time":5,"x":0,"y":0,"curve":[0.25000,0,0.75000,1]},{"time":7.50,"x":-58.32,"y":8.77,"curve":[0.25000,0,0.75000,1]},{"time":10,"x":0,"y":0}]},"bone190":{"rotate":[{"time":0,"angle":10.35,"curve":[0.30556,0.24242,0.65278,0.62121]},{"time":0.76667,"angle":5.94,"curve":[0.37500,0.50000,0.75000,1]},{"time":2,"angle":0,"curve":[0.25000,0,0.75000,1]},{"time":4.50,"angle":11.88,"curve":[0.28409,0,0.62500,0.38462]},{"time":5,"angle":10.35,"curve":[0.30556,0.24242,0.65278,0.62121]},{"time":5.77,"angle":5.94,"curve":[0.37500,0.50000,0.75000,1]},{"time":7,"angle":0,"curve":[0.25000,0,0.75000,1]},{"time":9.50,"angle":11.88,"curve":[0.28409,0,0.62500,0.38462]},{"time":10,"angle":10.35}],"translate":[{"time":0,"x":-11.49,"y":-0.52875,"curve":[0.38172,0.58333,0.73118,1]},{"time":0.76667,"x":0,"y":0,"curve":[0.25000,0,0.75000,1]},{"time":3.27,"x":-47.44,"y":-2.18,"curve":[0.24272,0,0.65534,0.62500]},{"time":5,"x":-11.49,"y":-0.52875,"curve":[0.38172,0.58333,0.73118,1]},{"time":5.77,"x":0,"y":0,"curve":[0.25000,0,0.75000,1]},{"time":8.27,"x":-47.44,"y":-2.18,"curve":[0.24272,0,0.65534,0.62500]},{"time":10,"x":-11.49,"y":-0.52875}]},"bone191":{"rotate":[{"time":0,"angle":-3.01,"curve":[0.37500,0.50000,0.75000,1]},{"time":1.27,"angle":0,"curve":[0.25000,0,0.75000,1]},{"time":3.77,"angle":-6.02,"curve":[0.25000,0,0.62500,0.50000]},{"time":5,"angle":-3.01,"curve":[0.37500,0.50000,0.75000,1]},{"time":6.27,"angle":0,"curve":[0.25000,0,0.75000,1]},{"time":8.77,"angle":-6.02,"curve":[0.25000,0,0.62500,0.50000]},{"time":10,"angle":-3.01}],"translate":[{"time":0,"x":0,"y":0,"curve":[0.25000,0,0.75000,1]},{"time":2.50,"x":-46.70,"y":-10.31,"curve":[0.25000,0,0.75000,1]},{"time":5,"x":0,"y":0,"curve":[0.25000,0,0.75000,1]},{"time":7.50,"x":-46.70,"y":-10.31,"curve":[0.25000,0,0.75000,1]},{"time":10,"x":0,"y":0}]},"bone192":{"rotate":[{"time":0,"angle":-2.76,"curve":[0.38172,0.58333,0.73118,1]},{"time":0.76667,"angle":0,"curve":[0.25000,0,0.75000,1]},{"time":3.27,"angle":-11.43,"curve":[0.25000,0,0.62500,0.50000]},{"time":4.50,"angle":-5.72,"curve":[0.33937,0.35211,0.67873,0.70423]},{"time":5,"angle":-2.76,"curve":[0.38172,0.58333,0.73118,1]},{"time":5.77,"angle":0,"curve":[0.25000,0,0.75000,1]},{"time":8.27,"angle":-11.43,"curve":[0.25000,0,0.62500,0.50000]},{"time":9.50,"angle":-5.72,"curve":[0.33937,0.35211,0.67873,0.70423]},{"time":10,"angle":-2.76}],"translate":[{"time":0,"x":-4.05,"y":-1.28,"curve":[0.32039,0.28571,0.75728,1]},{"time":2,"x":-31.10,"y":-9.84,"curve":[0.25000,0,0.75000,1]},{"time":4.50,"x":0,"y":0,"curve":[0.28409,0,0.62500,0.38462]},{"time":5,"x":-4.05,"y":-1.28,"curve":[0.32039,0.28571,0.75728,1]},{"time":7,"x":-31.10,"y":-9.84,"curve":[0.25000,0,0.75000,1]},{"time":9.50,"x":0,"y":0,"curve":[0.28409,0,0.62500,0.38462]},{"time":10,"x":-4.05,"y":-1.28}]},"bone193":{"rotate":[{"time":0,"angle":-8.26,"curve":[0.30556,0.24242,0.65278,0.62121]},{"time":0.76667,"angle":-4.74,"curve":[0.37500,0.50000,0.75000,1]},{"time":2,"angle":0,"curve":[0.25000,0,0.75000,1]},{"time":4.50,"angle":-9.48,"curve":[0.28409,0,0.62500,0.38462]},{"time":5,"angle":-8.26,"curve":[0.30556,0.24242,0.65278,0.62121]},{"time":5.77,"angle":-4.74,"curve":[0.37500,0.50000,0.75000,1]},{"time":7,"angle":0,"curve":[0.25000,0,0.75000,1]},{"time":9.50,"angle":-9.48,"curve":[0.28409,0,0.62500,0.38462]},{"time":10,"angle":-8.26}],"translate":[{"time":0,"x":1.71,"y":-6.86,"curve":[0.38172,0.58333,0.73118,1]},{"time":0.76667,"x":0,"y":0,"curve":[0.25000,0,0.75000,1]},{"time":3.27,"x":7.08,"y":-28.30,"curve":[0.24272,0,0.65534,0.62500]},{"time":5,"x":1.71,"y":-6.86,"curve":[0.38172,0.58333,0.73118,1]},{"time":5.77,"x":0,"y":0,"curve":[0.25000,0,0.75000,1]},{"time":8.27,"x":7.08,"y":-28.30,"curve":[0.24272,0,0.65534,0.62500]},{"time":10,"x":1.71,"y":-6.86}]},"bone194":{"rotate":[{"time":0,"angle":-7.96,"curve":[0.34466,0.37500,0.75728,1]},{"time":1.77,"angle":-0.93866,"curve":[0.25000,0,0.75000,1]},{"time":4.27,"angle":-10.20,"curve":[0.26882,0,0.61828,0.41667]},{"time":5,"angle":-7.96,"curve":[0.34466,0.37500,0.75728,1]},{"time":6.77,"angle":-0.93866,"curve":[0.25000,0,0.75000,1]},{"time":9.27,"angle":-10.20,"curve":[0.26882,0,0.61828,0.41667]},{"time":10,"angle":-7.96}],"translate":[{"time":0,"x":3.16,"y":0.06738,"curve":[0.38172,0.58333,0.73118,1]},{"time":0.76667,"x":15.90,"y":-7.34,"curve":[0.25000,0,0.75000,1]},{"time":3.27,"x":-36.69,"y":23.24,"curve":[0.24272,0,0.65534,0.62500]},{"time":5,"x":3.16,"y":0.06738,"curve":[0.38172,0.58333,0.73118,1]},{"time":5.77,"x":15.90,"y":-7.34,"curve":[0.25000,0,0.75000,1]},{"time":8.27,"x":-36.69,"y":23.24,"curve":[0.24272,0,0.65534,0.62500]},{"time":10,"x":3.16,"y":0.06738}]},"bone195":{"rotate":[{"time":0,"angle":-1.68,"curve":[0.38172,0.58333,0.73118,1]},{"time":0.76667,"angle":0,"curve":[0.25000,0,0.75000,1]},{"time":3.27,"angle":-6.94,"curve":[0.24272,0,0.65534,0.62500]},{"time":5,"angle":-1.68,"curve":[0.38172,0.58333,0.73118,1]},{"time":5.77,"angle":0,"curve":[0.25000,0,0.75000,1]},{"time":8.27,"angle":-6.94,"curve":[0.24272,0,0.65534,0.62500]},{"time":10,"angle":-1.68}],"translate":[{"time":0,"x":-0.50598,"y":-0.13794,"curve":[0.28922,0.16667,0.75490,1]},{"time":2.27,"x":-11.89,"y":-3.24,"curve":[0.25000,0,0.75000,1]},{"time":4.77,"x":0,"y":0,"curve":[0.30488,0,0.64024,0.35714]},{"time":5,"x":-0.50598,"y":-0.13794,"curve":[0.28922,0.16667,0.75490,1]},{"time":7.27,"x":-11.89,"y":-3.24,"curve":[0.25000,0,0.75000,1]},{"time":9.77,"x":0,"y":0,"curve":[0.30488,0,0.64024,0.35714]},{"time":10,"x":-0.50598,"y":-0.13794}]},"bone196":{"rotate":[{"time":0,"angle":-0.29922,"curve":[0.37500,0.61538,0.71591,1]},{"time":0.50000,"angle":0,"curve":[0.25000,0,0.75000,1]},{"time":3,"angle":-2.30,"curve":[0.24272,0,0.67961,0.71429]},{"time":5,"angle":-0.29922,"curve":[0.37500,0.61538,0.71591,1]},{"time":5.50,"angle":0,"curve":[0.25000,0,0.75000,1]},{"time":8,"angle":-2.30,"curve":[0.24272,0,0.67961,0.71429]},{"time":10,"angle":-0.29922}]},"bone197":{"rotate":[{"time":0,"angle":-3.11,"curve":[0.37500,0.50000,0.75000,1]},{"time":1.27,"angle":3.87,"curve":[0.25000,0,0.75000,1]},{"time":3.77,"angle":-10.10,"curve":[0.25000,0,0.62500,0.50000]},{"time":5,"angle":-3.11,"curve":[0.37500,0.50000,0.75000,1]},{"time":6.27,"angle":3.87,"curve":[0.25000,0,0.75000,1]},{"time":8.77,"angle":-10.10,"curve":[0.25000,0,0.62500,0.50000]},{"time":10,"angle":-3.11}]},"bone198":{"rotate":[{"time":0,"angle":-0.77275,"curve":[0.38172,0.58333,0.73118,1]},{"time":0.76667,"angle":0,"curve":[0.25000,0,0.75000,1]},{"time":3.27,"angle":-3.19,"curve":[0.24272,0,0.65534,0.62500]},{"time":5,"angle":-0.77275,"curve":[0.38172,0.58333,0.73118,1]},{"time":5.77,"angle":0,"curve":[0.25000,0,0.75000,1]},{"time":8.27,"angle":-3.19,"curve":[0.24272,0,0.65534,0.62500]},{"time":10,"angle":-0.77275}]},"bone199":{"rotate":[{"time":0,"angle":-3.39,"curve":[0.36275,0.44444,0.75490,1]},{"time":1.50,"angle":2.89,"curve":[0.25000,0,0.75000,1]},{"time":4,"angle":-7.04,"curve":[0.25773,0,0.61856,0.45455]},{"time":5,"angle":-3.39,"curve":[0.36275,0.44444,0.75490,1]},{"time":6.50,"angle":2.89,"curve":[0.25000,0,0.75000,1]},{"time":9,"angle":-7.04,"curve":[0.25773,0,0.61856,0.45455]},{"time":10,"angle":-3.39}]},"bone200":{"rotate":[{"time":0,"angle":0,"curve":[0.25000,0,0.75000,1]},{"time":2.50,"angle":-0.36451,"curve":[0.25000,0,0.75000,1]},{"time":5,"angle":0,"curve":[0.25000,0,0.75000,1]},{"time":7.50,"angle":-0.36451,"curve":[0.25000,0,0.75000,1]},{"time":10,"angle":0}]},"bone201":{"translate":[{"time":0,"x":0,"y":0,"curve":[0.25000,0,0.75000,1]},{"time":5,"x":0,"y":15.48,"curve":[0.25000,0,0.75000,1]},{"time":10,"x":0,"y":0}],"scale":[{"time":0,"x":1,"y":1,"curve":[0.25000,0,0.75000,1]},{"time":5,"x":0.99000,"y":0.99000,"curve":[0.25000,0,0.75000,1]},{"time":10,"x":1,"y":1}]},"bone202":{"rotate":[{"time":0,"angle":7.61,"curve":[0.30556,0.24242,0.65278,0.62121]},{"time":0.76667,"angle":4.37,"curve":[0.37500,0.50000,0.75000,1]},{"time":2,"angle":0,"curve":[0.25000,0,0.75000,1]},{"time":4.50,"angle":8.74,"curve":[0.28409,0,0.62500,0.38462]},{"time":5,"angle":7.61,"curve":[0.30556,0.24242,0.65278,0.62121]},{"time":5.77,"angle":4.37,"curve":[0.37500,0.50000,0.75000,1]},{"time":7,"angle":0,"curve":[0.25000,0,0.75000,1]},{"time":9.50,"angle":8.74,"curve":[0.28409,0,0.62500,0.38462]},{"time":10,"angle":7.61}],"translate":[{"time":0,"x":-6.46,"y":-7.18,"curve":[0.38172,0.58333,0.73118,1]},{"time":0.76667,"x":0,"y":0,"curve":[0.25000,0,0.75000,1]},{"time":3.27,"x":-26.69,"y":-29.65,"curve":[0.24272,0,0.65534,0.62500]},{"time":5,"x":-6.46,"y":-7.18,"curve":[0.38172,0.58333,0.73118,1]},{"time":5.77,"x":0,"y":0,"curve":[0.25000,0,0.75000,1]},{"time":8.27,"x":-26.69,"y":-29.65,"curve":[0.24272,0,0.65534,0.62500]},{"time":10,"x":-6.46,"y":-7.18}]},"bone203":{"rotate":[{"time":0,"angle":4.07,"curve":[0.37500,0.50000,0.75000,1]},{"time":1.27,"angle":0,"curve":[0.25000,0,0.75000,1]},{"time":3.77,"angle":8.14,"curve":[0.25000,0,0.62500,0.50000]},{"time":5,"angle":4.07,"curve":[0.37500,0.50000,0.75000,1]},{"time":6.27,"angle":0,"curve":[0.25000,0,0.75000,1]},{"time":8.77,"angle":8.14,"curve":[0.25000,0,0.62500,0.50000]},{"time":10,"angle":4.07}],"translate":[{"time":0,"x":0,"y":0,"curve":[0.25000,0,0.75000,1]},{"time":2.50,"x":-27.92,"y":1.52,"curve":[0.25000,0,0.75000,1]},{"time":5,"x":0,"y":0,"curve":[0.25000,0,0.75000,1]},{"time":7.50,"x":-27.92,"y":1.52,"curve":[0.25000,0,0.75000,1]},{"time":10,"x":0,"y":0}]},"bone204":{"scale":[{"time":0,"x":0.20872,"y":0.89953,"curve":"stepped"},{"time":2.67,"x":0.20872,"y":0.89953,"curve":[0.21356,0.20139,0.16014,0.98611]},{"time":5.67,"x":1,"y":1,"curve":[0.25000,0,0.75000,1]},{"time":7.33,"x":0.20872,"y":0.89953}]},"bone210":{"translate":[{"time":0,"x":-5.53,"y":19.53,"curve":[0.30468,0.22680,0.75631,1]},{"time":2.13,"x":-68.83,"y":243.22,"curve":[0.25000,0,0.75000,1]},{"time":4.63,"x":0,"y":0,"curve":[0.25000,0,0.75000,1]},{"time":7.13,"x":-68.83,"y":243.22,"curve":[0.25000,0,0.75000,1]},{"time":9.63,"x":0,"y":0,"curve":[0.29438,0,0.63193,0.36946]},{"time":10,"x":-5.53,"y":19.53}]},"bone211":{"translate":[{"time":0,"x":-91.16,"y":-60.77,"curve":[0.38144,0.54545,0.74227,1]},{"time":1,"x":0,"y":0,"curve":[0.25000,0,0.75000,1]},{"time":3.50,"x":-247.81,"y":-165.20,"curve":[0.25000,0,0.75000,1]},{"time":6,"x":0,"y":0,"curve":[0.25000,0,0.75000,1]},{"time":8.50,"x":-247.81,"y":-165.20,"curve":[0.24510,0,0.63725,0.55556]},{"time":10,"x":-91.16,"y":-60.77}]},"bone212":{"translate":[{"time":0,"x":313.92,"y":103.14,"curve":[0.27711,0.11765,0.75356,1]},{"time":2.33,"x":0,"y":0,"curve":[0.25000,0,0.75000,1]},{"time":4.83,"x":321.23,"y":105.55,"curve":[0.25000,0,0.75000,1]},{"time":7.33,"x":0,"y":0,"curve":[0.25000,0,0.75000,1]},{"time":9.83,"x":321.23,"y":105.55,"curve":[0.31337,0,0.64763,0.34884]},{"time":10,"x":313.92,"y":103.14}]}}}}}