{"skeleton":{"hash":"3l44JppuvwPRF3nY/avf048T8Sw","spine":"3.7.93","width":1026.91,"height":1451.06},"bones":[{"name":"root"}],"slots":[{"name":"CLB_003_4","bone":"root","attachment":"CLB_003_4"}],"skins":{"default":{"CLB_003_4":{"CLB_003_4":{"type":"mesh","width":32,"height":32,"hull":4,"triangles":[1,2,3,1,3,0],"uvs":[1,1,0,1,0,0,1,0],"vertices":[513.46,-723.47,-510.54,-725.53,-513.46,723.47,510.54,725.53]}}}},"animations":{"BASE":{"slots":{"CLB_003_4":{"attachment":[{"time":2,"name":"CLB_003_4"}]}}},"DESPAIR":{"slots":{"CLB_003_4":{"attachment":[{"time":2,"name":"CLB_003_4"}]}}},"HATE":{"slots":{"CLB_003_4":{"attachment":[{"time":2,"name":"CLB_003_4"}]}}},"IDLE":{"slots":{"CLB_003_4":{"attachment":[{"time":2,"name":"CLB_003_4"}]}}},"LAUGH":{"slots":{"CLB_003_4":{"attachment":[{"time":2,"name":"CLB_003_4"}]}}},"NOANI":{"slots":{"CLB_003_4":{"attachment":[{"time":0,"name":null},{"time":2,"name":null}]}}},"PRIDE":{"slots":{"CLB_003_4":{"attachment":[{"time":2,"name":"CLB_003_4"}]}}},"SERIOUS":{"slots":{"CLB_003_4":{"attachment":[{"time":2,"name":"CLB_003_4"}]}}},"START":{"slots":{"CLB_003_4":{"attachment":[{"time":2,"name":"CLB_003_4"}]}}},"SURPRISE":{"slots":{"CLB_003_4":{"attachment":[{"time":2,"name":"CLB_003_4"}]}}},"TOUCH":{"slots":{"CLB_003_4":{"attachment":[{"time":2,"name":"CLB_003_4"}]}}}}}